{"Algorithm Parameters": {"Eps": 2.1, "MinPts": 1, "K": 42}, "Algorithm Performance": {"Calinski Harabasz Index": 12.347}, "Clusters Content Analysis": {"Predictive Power": {"Global": {"Metrics": {"Class: Upgrade": "No element of this class", "Class: Downgrade": "No element of this class"}, "Confusion Matrix": {"predicted_down_AND_was_down": 0, "predicted_up_AND_was_up": 0, "predicted_no_change_AND_was_no_change": 40, "predicted_down_BUT_was_up": 0, "predicted_down_BUT_was_no_change": 4, "predicted_no_change_BUT_was_up": 0, "predicted_no_change_BUT_was_down": 0, "predicted_up_BUT_was_down": 0, "predicted_up_BUT_was_no_change": 4}}, "Restricted to jumps to or from below B-": {"Metrics": {"Class: Upgrade": "No element of this class", "Class: Downgrade": "No element of this class"}, "Confusion Matrix": {"predicted_down_AND_was_down": 0, "predicted_up_AND_was_up": 0, "predicted_no_change_AND_was_no_change": 40, "predicted_down_BUT_was_up": 0, "predicted_down_BUT_was_no_change": 4, "predicted_no_change_BUT_was_up": 0, "predicted_no_change_BUT_was_down": 0, "predicted_up_BUT_was_down": 0, "predicted_up_BUT_was_no_change": 4}}}, "Share of total companies in each clusters": [0.020833333333333332, 0.020833333333333332, 0.020833333333333332, 0.020833333333333332, 0.020833333333333332, 0.020833333333333332, 0.020833333333333332, 0.041666666666666664, 0.020833333333333332, 0.020833333333333332, 0.020833333333333332, 0.020833333333333332, 0.020833333333333332, 0.020833333333333332, 0.020833333333333332, 0.020833333333333332, 0.020833333333333332, 0.020833333333333332, 0.020833333333333332, 0.020833333333333332, 0.020833333333333332, 0.020833333333333332, 0.125, 0.020833333333333332, 0.020833333333333332, 0.020833333333333332, 0.020833333333333332, 0.020833333333333332, 0.020833333333333332, 0.020833333333333332, 0.020833333333333332, 0.020833333333333332, 0.020833333333333332, 0.020833333333333332, 0.020833333333333332, 0.020833333333333332, 0.020833333333333332, 0.020833333333333332, 0.020833333333333332, 0.020833333333333332, 0.020833333333333332, 0.020833333333333332, {"SUM": 1.0000000000000004}], "Clusters with significant ranges (count)": 1, "Significant Clusters (count)": 1, "Cluster Credit Ratings Shares": [{"AA": 1.0}, {"AA-": 1.0}, {"AA-": 1.0}, {"AA-": 1.0}, {"AA-": 1.0}, {"A+": 1.0}, {"A": 1.0}, {"A-": 0.5, "BBB-": 0.5}, {"A-": 1.0}, {"A-": 1.0}, {"A-": 1.0}, {"BBB+": 1.0}, {"BBB+": 1.0}, {"BBB+": 1.0}, {"BBB+": 1.0}, {"BBB": 1.0}, {"BBB": 1.0}, {"BBB": 1.0}, {"BBB": 1.0}, {"BBB": 1.0}, {"BBB-": 1.0}, {"BBB-": 1.0}, {"BBB-": 0.16666666666666666, "BB+": 0.3333333333333333, "BB-": 0.16666666666666666, "B": 0.3333333333333333}, {"BBB-": 1.0}, {"BBB-": 1.0}, {"BBB-": 1.0}, {"BB": 1.0}, {"BB": 1.0}, {"BB": 1.0}, {"BB-": 1.0}, {"BB-": 1.0}, {"BB-": 1.0}, {"BB-": 1.0}, {"BB-": 1.0}, {"B+": 1.0}, {"B+": 1.0}, {"B+": 1.0}, {"B+": 1.0}, {"B+": 1.0}, {"B+": 1.0}, {"B+": 1.0}, {"B": 1.0}], "Share of total companies with given credit rating in each cluter": [{"AA": 1.0}, {"AA-": 0.25}, {"AA-": 0.25}, {"AA-": 0.25}, {"AA-": 0.25}, {"A+": 1.0}, {"A": 1.0}, {"A-": 0.25, "BBB-": 0.14285714285714285}, {"A-": 0.25}, {"A-": 0.25}, {"A-": 0.25}, {"BBB+": 0.25}, {"BBB+": 0.25}, {"BBB+": 0.25}, {"BBB+": 0.25}, {"BBB": 0.2}, {"BBB": 0.2}, {"BBB": 0.2}, {"BBB": 0.2}, {"BBB": 0.2}, {"BBB-": 0.14285714285714285}, {"BBB-": 0.14285714285714285}, {"BBB-": 0.14285714285714285, "BB+": 1.0, "BB-": 0.16666666666666666, "B": 0.6666666666666666}, {"BBB-": 0.14285714285714285}, {"BBB-": 0.14285714285714285}, {"BBB-": 0.14285714285714285}, {"BB": 0.3333333333333333}, {"BB": 0.3333333333333333}, {"BB": 0.3333333333333333}, {"BB-": 0.16666666666666666}, {"BB-": 0.16666666666666666}, {"BB-": 0.16666666666666666}, {"BB-": 0.16666666666666666}, {"BB-": 0.16666666666666666}, {"B+": 0.14285714285714285}, {"B+": 0.14285714285714285}, {"B+": 0.14285714285714285}, {"B+": 0.14285714285714285}, {"B+": 0.14285714285714285}, {"B+": 0.14285714285714285}, {"B+": 0.14285714285714285}, {"B": 0.3333333333333333}], "Cluster ranges": [0.0, 0.0, 0.0, 0.0, 0.0, 0.0, 0.0, 3.0, 0.0, 0.0, 0.0, 0.0, 0.0, 0.0, 0.0, 0.0, 0.0, 0.0, 0.0, 0.0, 0.0, 0.0, 5.0, 0.0, 0.0, 0.0, 0.0, 0.0, 0.0, 0.0, 0.0, 0.0, 0.0, 0.0, 0.0, 0.0, 0.0, 0.0, 0.0, 0.0, 0.0, 0.0], "Cluster metrics of location and dispersion": [{"Mean": 3.0, "Median": 3.0, "1st Quartile": 3.0, "3rd Quartile": 3.0, "Standard Deviation": 0.0, "Is Signficant": false}, {"Mean": 4.0, "Median": 4.0, "1st Quartile": 4.0, "3rd Quartile": 4.0, "Standard Deviation": 0.0, "Is Signficant": false}, {"Mean": 4.0, "Median": 4.0, "1st Quartile": 4.0, "3rd Quartile": 4.0, "Standard Deviation": 0.0, "Is Signficant": false}, {"Mean": 4.0, "Median": 4.0, "1st Quartile": 4.0, "3rd Quartile": 4.0, "Standard Deviation": 0.0, "Is Signficant": false}, {"Mean": 4.0, "Median": 4.0, "1st Quartile": 4.0, "3rd Quartile": 4.0, "Standard Deviation": 0.0, "Is Signficant": false}, {"Mean": 5.0, "Median": 5.0, "1st Quartile": 5.0, "3rd Quartile": 5.0, "Standard Deviation": 0.0, "Is Signficant": false}, {"Mean": 6.0, "Median": 6.0, "1st Quartile": 6.0, "3rd Quartile": 6.0, "Standard Deviation": 0.0, "Is Signficant": false}, {"Mean": 8.5, "Median": 8.5, "1st Quartile": 7.75, "3rd Quartile": 9.25, "Standard Deviation": 1.5, "Is Signficant": false}, {"Mean": 7.0, "Median": 7.0, "1st Quartile": 7.0, "3rd Quartile": 7.0, "Standard Deviation": 0.0, "Is Signficant": false}, {"Mean": 7.0, "Median": 7.0, "1st Quartile": 7.0, "3rd Quartile": 7.0, "Standard Deviation": 0.0, "Is Signficant": false}, {"Mean": 7.0, "Median": 7.0, "1st Quartile": 7.0, "3rd Quartile": 7.0, "Standard Deviation": 0.0, "Is Signficant": false}, {"Mean": 8.0, "Median": 8.0, "1st Quartile": 8.0, "3rd Quartile": 8.0, "Standard Deviation": 0.0, "Is Signficant": false}, {"Mean": 8.0, "Median": 8.0, "1st Quartile": 8.0, "3rd Quartile": 8.0, "Standard Deviation": 0.0, "Is Signficant": false}, {"Mean": 8.0, "Median": 8.0, "1st Quartile": 8.0, "3rd Quartile": 8.0, "Standard Deviation": 0.0, "Is Signficant": false}, {"Mean": 8.0, "Median": 8.0, "1st Quartile": 8.0, "3rd Quartile": 8.0, "Standard Deviation": 0.0, "Is Signficant": false}, {"Mean": 9.0, "Median": 9.0, "1st Quartile": 9.0, "3rd Quartile": 9.0, "Standard Deviation": 0.0, "Is Signficant": false}, {"Mean": 9.0, "Median": 9.0, "1st Quartile": 9.0, "3rd Quartile": 9.0, "Standard Deviation": 0.0, "Is Signficant": false}, {"Mean": 9.0, "Median": 9.0, "1st Quartile": 9.0, "3rd Quartile": 9.0, "Standard Deviation": 0.0, "Is Signficant": false}, {"Mean": 9.0, "Median": 9.0, "1st Quartile": 9.0, "3rd Quartile": 9.0, "Standard Deviation": 0.0, "Is Signficant": false}, {"Mean": 9.0, "Median": 9.0, "1st Quartile": 9.0, "3rd Quartile": 9.0, "Standard Deviation": 0.0, "Is Signficant": false}, {"Mean": 10.0, "Median": 10.0, "1st Quartile": 10.0, "3rd Quartile": 10.0, "Standard Deviation": 0.0, "Is Signficant": false}, {"Mean": 10.0, "Median": 10.0, "1st Quartile": 10.0, "3rd Quartile": 10.0, "Standard Deviation": 0.0, "Is Signficant": false}, {"Mean": 12.5, "Median": 12.0, "1st Quartile": 11.0, "3rd Quartile": 14.5, "Standard Deviation": 1.9790570145063195, "Is Signficant": true}, {"Mean": 10.0, "Median": 10.0, "1st Quartile": 10.0, "3rd Quartile": 10.0, "Standard Deviation": 0.0, "Is Signficant": false}, {"Mean": 10.0, "Median": 10.0, "1st Quartile": 10.0, "3rd Quartile": 10.0, "Standard Deviation": 0.0, "Is Signficant": false}, {"Mean": 10.0, "Median": 10.0, "1st Quartile": 10.0, "3rd Quartile": 10.0, "Standard Deviation": 0.0, "Is Signficant": false}, {"Mean": 12.0, "Median": 12.0, "1st Quartile": 12.0, "3rd Quartile": 12.0, "Standard Deviation": 0.0, "Is Signficant": false}, {"Mean": 12.0, "Median": 12.0, "1st Quartile": 12.0, "3rd Quartile": 12.0, "Standard Deviation": 0.0, "Is Signficant": false}, {"Mean": 12.0, "Median": 12.0, "1st Quartile": 12.0, "3rd Quartile": 12.0, "Standard Deviation": 0.0, "Is Signficant": false}, {"Mean": 13.0, "Median": 13.0, "1st Quartile": 13.0, "3rd Quartile": 13.0, "Standard Deviation": 0.0, "Is Signficant": false}, {"Mean": 13.0, "Median": 13.0, "1st Quartile": 13.0, "3rd Quartile": 13.0, "Standard Deviation": 0.0, "Is Signficant": false}, {"Mean": 13.0, "Median": 13.0, "1st Quartile": 13.0, "3rd Quartile": 13.0, "Standard Deviation": 0.0, "Is Signficant": false}, {"Mean": 13.0, "Median": 13.0, "1st Quartile": 13.0, "3rd Quartile": 13.0, "Standard Deviation": 0.0, "Is Signficant": false}, {"Mean": 13.0, "Median": 13.0, "1st Quartile": 13.0, "3rd Quartile": 13.0, "Standard Deviation": 0.0, "Is Signficant": false}, {"Mean": 14.0, "Median": 14.0, "1st Quartile": 14.0, "3rd Quartile": 14.0, "Standard Deviation": 0.0, "Is Signficant": false}, {"Mean": 14.0, "Median": 14.0, "1st Quartile": 14.0, "3rd Quartile": 14.0, "Standard Deviation": 0.0, "Is Signficant": false}, {"Mean": 14.0, "Median": 14.0, "1st Quartile": 14.0, "3rd Quartile": 14.0, "Standard Deviation": 0.0, "Is Signficant": false}, {"Mean": 14.0, "Median": 14.0, "1st Quartile": 14.0, "3rd Quartile": 14.0, "Standard Deviation": 0.0, "Is Signficant": false}, {"Mean": 14.0, "Median": 14.0, "1st Quartile": 14.0, "3rd Quartile": 14.0, "Standard Deviation": 0.0, "Is Signficant": false}, {"Mean": 14.0, "Median": 14.0, "1st Quartile": 14.0, "3rd Quartile": 14.0, "Standard Deviation": 0.0, "Is Signficant": false}, {"Mean": 14.0, "Median": 14.0, "1st Quartile": 14.0, "3rd Quartile": 14.0, "Standard Deviation": 0.0, "Is Signficant": false}, {"Mean": 15.0, "Median": 15.0, "1st Quartile": 15.0, "3rd Quartile": 15.0, "Standard Deviation": 0.0, "Is Signficant": false}], "Cluster entropies": [0, 0, 0, 0, 0, 0, 0, 1.0, 0, 0, 0, 0, 0, 0, 0, 0, 0, 0, 0, 0, 0, 0, 1.9182958340544896, 0, 0, 0, 0, 0, 0, 0, 0, 0, 0, 0, 0, 0, 0, 0, 0, 0, 0, 0], "Maximum entropy": 1.9182958340544896, "Weighted average entropy": 0.2814536459234779, "Incoherencies explanations": {"CLUSTER 0": {"RATING BB+": [{"0": {"Comparison": "Cluster elements are located around median", "Credit Rating Statistics": {"Mean": -1.5679077957533818, "Median": -1.5679077957533818, "1st Quartile": -1.6046651198125559, "3rd Quartile": -1.5311504716942077, "Standard Deviation": 0.07351464811834818}, "Cluster Statistics": {"Mean": -1.5679077957533818, "Median": -1.5679077957533818, "1st Quartile": -1.6046651198125559, "3rd Quartile": -1.5311504716942077, "Standard Deviation": 0.07351464811834818}}}, {"1": {"Comparison": "Cluster elements are located around median", "Credit Rating Statistics": {"Mean": -0.36363139063876215, "Median": -0.36363139063876215, "1st Quartile": -0.5543114381952621, "3rd Quartile": -0.17295134308226212, "Standard Deviation": 0.38136009511299995}, "Cluster Statistics": {"Mean": -0.36363139063876215, "Median": -0.36363139063876215, "1st Quartile": -0.5543114381952621, "3rd Quartile": -0.17295134308226212, "Standard Deviation": 0.38136009511299995}}}, {"2": {"Comparison": "Cluster elements are located around median", "Credit Rating Statistics": {"Mean": -1.2667127022499671, "Median": -1.2667127022499671, "1st Quartile": -1.5315052175012336, "3rd Quartile": -1.001920186998701, "Standard Deviation": 0.5295850305025326}, "Cluster Statistics": {"Mean": -1.2667127022499671, "Median": -1.2667127022499671, "1st Quartile": -1.5315052175012336, "3rd Quartile": -1.001920186998701, "Standard Deviation": 0.5295850305025326}}}, {"3": {"Comparison": "Cluster elements are located around median", "Credit Rating Statistics": {"Mean": -0.4478001196892655, "Median": -0.4478001196892655, "1st Quartile": -0.4742396912372755, "3rd Quartile": -0.4213605481412554, "Standard Deviation": 0.05287914309602007}, "Cluster Statistics": {"Mean": -0.4478001196892655, "Median": -0.4478001196892655, "1st Quartile": -0.4742396912372755, "3rd Quartile": -0.4213605481412554, "Standard Deviation": 0.05287914309602007}}}, {"5": {"Comparison": "Cluster elements are located around median", "Credit Rating Statistics": {"Mean": -0.15110641003113598, "Median": -0.15110641003113598, "1st Quartile": -0.15669733080808623, "3rd Quartile": -0.14551548925418573, "Standard Deviation": 0.011181841553900479}, "Cluster Statistics": {"Mean": -0.15110641003113598, "Median": -0.15110641003113598, "1st Quartile": -0.15669733080808623, "3rd Quartile": -0.14551548925418573, "Standard Deviation": 0.011181841553900479}}}], "RATING B": [{"0": {"Comparison": "Cluster elements in lowest 25%", "Credit Rating Statistics": {"Mean": -1.6841419307058771, "Median": -3.0688412206343902, "1st Quartile": -3.3679464811592688, "3rd Quartile": -0.6926870252167427, "Standard Deviation": 2.393749812777197}, "Cluster Statistics": {"Mean": -3.3679464811592688, "Median": -3.3679464811592688, "1st Quartile": -3.517499111421708, "3rd Quartile": -3.2183938508968293, "Standard Deviation": 0.2991052605248783}}}, {"2": {"Comparison": "Cluster elements in lowest 25%", "Credit Rating Statistics": {"Mean": 0.5266111483810383, "Median": 0.19067823979697623, "1st Quartile": -0.21948676858959232, "3rd Quartile": 1.104742611059638, "Standard Deviation": 1.107014495306632}, "Cluster Statistics": {"Mean": -0.21948676858959235, "Median": -0.21948676858959235, "1st Quartile": -0.42456927278287665, "3rd Quartile": -0.014404264396308042, "Standard Deviation": 0.41016500838656855}}}, {"3": {"Comparison": "Cluster elements in highest 75%", "Credit Rating Statistics": {"Mean": -1.384518106809389, "Median": -1.6103802950197914, "1st Quartile": -1.685141879930658, "3rd Quartile": -1.1968254277933217, "Standard Deviation": 0.4295061144115713}, "Cluster Statistics": {"Mean": -1.1968254277933217, "Median": -1.1968254277933217, "1st Quartile": -1.4036028614065565, "3rd Quartile": -0.9900479941800868, "Standard Deviation": 0.4135548672264697}}}, {"4": {"Comparison": "Cluster elements in highest 75%", "Credit Rating Statistics": {"Mean": -0.7058329836225714, "Median": -0.38164625223986187, "1st Quartile": -0.925906981370749, "3rd Quartile": -0.3236656201830392, "Standard Deviation": 0.5425356730075785}, "Cluster Statistics": {"Mean": -0.3236656201830392, "Median": -0.3236656201830392, "1st Quartile": -0.3526559362114505, "3rd Quartile": -0.29467530415462784, "Standard Deviation": 0.05798063205682269}}}, {"5": {"Comparison": "Cluster elements in lowest 25%", "Credit Rating Statistics": {"Mean": 0.2026430838640095, "Median": 0.14969798889178948, "1st Quartile": 0.05452814076140451, "3rd Quartile": 0.32428547948050446, "Standard Deviation": 0.22341502352352263}, "Cluster Statistics": {"Mean": 0.05452814076140451, "Median": 0.05452814076140451, "1st Quartile": 0.006943216696212021, "3rd Quartile": 0.10211306482659699, "Standard Deviation": 0.09516984813038498}}}]}}}}