{"Algorithm Parameters": {"K": 12}, "Algorithm Performance": {"WCSS": 472.04251337431754, "Silhouette Score": 0.14783023785349877, "Calinski Harabasz Index": 8.521842676134245}, "Clusters Content Analysis": {"Predictive Power": {"Global": {"Metrics": {"Class: Upgrade": "No element of this class", "Class: Downgrade": "No element of this class"}, "Confusion Matrix": {"predicted_down_AND_was_down": 0, "predicted_up_AND_was_up": 0, "predicted_no_change_AND_was_no_change": 8, "predicted_down_BUT_was_up": 0, "predicted_down_BUT_was_no_change": 22, "predicted_no_change_BUT_was_up": 0, "predicted_no_change_BUT_was_down": 0, "predicted_up_BUT_was_down": 0, "predicted_up_BUT_was_no_change": 18}}, "Restricted to jumps to or from below B-": {"Metrics": {"Class: Upgrade": "No element of this class", "Class: Downgrade": "No element of this class"}, "Confusion Matrix": {"predicted_down_AND_was_down": 0, "predicted_up_AND_was_up": 0, "predicted_no_change_AND_was_no_change": 8, "predicted_down_BUT_was_up": 0, "predicted_down_BUT_was_no_change": 22, "predicted_no_change_BUT_was_up": 0, "predicted_no_change_BUT_was_down": 0, "predicted_up_BUT_was_down": 0, "predicted_up_BUT_was_no_change": 18}}}, "Share of total companies in each clusters": [0.020833333333333332, 0.08333333333333333, 0.14583333333333334, 0.020833333333333332, 0.4583333333333333, 0.041666666666666664, 0.08333333333333333, 0.020833333333333332, 0.0625, 0.020833333333333332, 0.020833333333333332, 0.020833333333333332, {"SUM": 1.0}], "Clusters with significant ranges (count)": 3, "Significant Clusters (count)": 3, "Cluster Credit Ratings Shares": [{"AA": 1.0}, {"AA-": 0.5, "A+": 0.25, "A-": 0.25}, {"AA-": 0.14285714285714285, "A": 0.14285714285714285, "A-": 0.2857142857142857, "BBB": 0.14285714285714285, "B+": 0.2857142857142857}, {"AA-": 1.0}, {"A-": 0.045454545454545456, "BBB": 0.13636363636363635, "BBB-": 0.2727272727272727, "BB+": 0.09090909090909091, "BB": 0.09090909090909091, "BB-": 0.22727272727272727, "B+": 0.045454545454545456, "B": 0.09090909090909091}, {"BBB+": 0.5, "B": 0.5}, {"BBB+": 0.5, "BBB": 0.25, "BBB-": 0.25}, {"BBB+": 1.0}, {"BB": 0.3333333333333333, "BB-": 0.3333333333333333, "B+": 0.3333333333333333}, {"B+": 1.0}, {"B+": 1.0}, {"B+": 1.0}], "Share of total companies with given credit rating in each cluter": [{"AA": 1.0}, {"AA-": 0.5, "A+": 1.0, "A-": 0.25}, {"AA-": 0.25, "A": 1.0, "A-": 0.5, "BBB": 0.2, "B+": 0.2857142857142857}, {"AA-": 0.25}, {"A-": 0.25, "BBB": 0.6, "BBB-": 0.8571428571428571, "BB+": 1.0, "BB": 0.6666666666666666, "BB-": 0.8333333333333334, "B+": 0.14285714285714285, "B": 0.6666666666666666}, {"BBB+": 0.25, "B": 0.3333333333333333}, {"BBB+": 0.5, "BBB": 0.2, "BBB-": 0.14285714285714285}, {"BBB+": 0.25}, {"BB": 0.3333333333333333, "BB-": 0.16666666666666666, "B+": 0.14285714285714285}, {"B+": 0.14285714285714285}, {"B+": 0.14285714285714285}, {"B+": 0.14285714285714285}], "Cluster ranges": [0.0, 3.0, 10.0, 0.0, 8.0, 7.0, 2.0, 0.0, 2.0, 0.0, 0.0, 0.0], "Cluster metrics of location and dispersion": [{"Mean": 3.0, "Median": 3.0, "1st Quartile": 3.0, "3rd Quartile": 3.0, "Standard Deviation": 0.0, "Is Signficant": false}, {"Mean": 5.0, "Median": 4.5, "1st Quartile": 4.0, "3rd Quartile": 5.5, "Standard Deviation": 1.224744871391589, "Is Signficant": false}, {"Mean": 8.714285714285714, "Median": 7.0, "1st Quartile": 6.5, "3rd Quartile": 11.5, "Standard Deviation": 3.614031611621005, "Is Signficant": true}, {"Mean": 4.0, "Median": 4.0, "1st Quartile": 4.0, "3rd Quartile": 4.0, "Standard Deviation": 0.0, "Is Signficant": false}, {"Mean": 11.318181818181818, "Median": 11.0, "1st Quartile": 10.0, "3rd Quartile": 13.0, "Standard Deviation": 2.07553637396925, "Is Signficant": true}, {"Mean": 11.5, "Median": 11.5, "1st Quartile": 9.75, "3rd Quartile": 13.25, "Standard Deviation": 3.5, "Is Signficant": true}, {"Mean": 8.75, "Median": 8.5, "1st Quartile": 8.0, "3rd Quartile": 9.25, "Standard Deviation": 0.82915619758885, "Is Signficant": false}, {"Mean": 8.0, "Median": 8.0, "1st Quartile": 8.0, "3rd Quartile": 8.0, "Standard Deviation": 0.0, "Is Signficant": false}, {"Mean": 13.0, "Median": 13.0, "1st Quartile": 12.5, "3rd Quartile": 13.5, "Standard Deviation": 0.816496580927726, "Is Signficant": false}, {"Mean": 14.0, "Median": 14.0, "1st Quartile": 14.0, "3rd Quartile": 14.0, "Standard Deviation": 0.0, "Is Signficant": false}, {"Mean": 14.0, "Median": 14.0, "1st Quartile": 14.0, "3rd Quartile": 14.0, "Standard Deviation": 0.0, "Is Signficant": false}, {"Mean": 14.0, "Median": 14.0, "1st Quartile": 14.0, "3rd Quartile": 14.0, "Standard Deviation": 0.0, "Is Signficant": false}], "Cluster entropies": [0, 1.5, 2.2359263506290326, 0, 2.7378723922315147, 1.0, 1.5, 0, 1.584962500721156, 0, 0, 0], "Maximum entropy": 2.7378723922315147, "Weighted average entropy": 1.9716575955345839, "Incoherencies explanations": {"CLUSTER 0": {"RATING A-": [{"0": {"Comparison": "Cluster elements in highest 75%", "Credit Rating Statistics": {"Mean": 0.3389482631672633, "Median": 0.6453829910949384, "1st Quartile": 0.10964960684503688, "3rd Quartile": 0.8746816474171647, "Standard Deviation": 1.0810228604356256}, "Cluster Statistics": {"Mean": 1.08260325690736, "Median": 1.08260325690736, "1st Quartile": 0.8746816474171647, "3rd Quartile": 1.2905248663975553, "Standard Deviation": 0.4158432189803905}}}, {"1": {"Comparison": "Cluster elements in lowest 25%", "Credit Rating Statistics": {"Mean": -1.4041425170367445, "Median": -1.0508906280180197, "1st Quartile": -2.276476080972019, "3rd Quartile": -0.17855706408274485, "Standard Deviation": 2.1297090063668738}, "Cluster Statistics": {"Mean": -3.0836220556867655, "Median": -3.0836220556867655, "1st Quartile": -3.8907680304015115, "3rd Quartile": -2.276476080972019, "Standard Deviation": 1.6142919494294923}}}, {"2": {"Comparison": "Cluster elements in highest 75%", "Credit Rating Statistics": {"Mean": -1.0906311835392546, "Median": -1.2417753021755567, "1st Quartile": -1.9381983253223, "3rd Quartile": -0.39420816039251116, "Standard Deviation": 1.5880470386862848}, "Cluster Statistics": {"Mean": 0.16293150523639754, "Median": 0.16293150523639754, "1st Quartile": -0.39420816039251116, "3rd Quartile": 0.7200711708653063, "Standard Deviation": 1.1142793312578174}}}, {"3": {"Comparison": "Cluster elements in lower half", "Credit Rating Statistics": {"Mean": 0.7204834122561576, "Median": 0.38573674753446846, "1st Quartile": -0.0423655692052658, "3rd Quartile": 1.1485857289958918, "Standard Deviation": 1.0006147701514896}, "Cluster Statistics": {"Mean": 0.26268425257128547, "Median": 0.26268425257128547, "1st Quartile": 0.01786997046062261, "3rd Quartile": 0.5074985346819483, "Standard Deviation": 0.4896285642213257}}}, {"13": {"Comparison": "Cluster elements in upper half", "Credit Rating Statistics": {"Mean": 0.32185488272804896, "Median": 0.36531280743256334, "1st Quartile": 0.26235547435751944, "3rd Quartile": 0.4248122158030929, "Standard Deviation": 0.1235991715137594}, "Cluster Statistics": {"Mean": 0.36991029308776724, "Median": 0.36991029308776724, "1st Quartile": 0.3390112174887015, "3rd Quartile": 0.40080936868683303, "Standard Deviation": 0.06179815119813151}}}], "RATING B+": [{"0": {"Comparison": "Cluster elements in upper half", "Credit Rating Statistics": {"Mean": -0.14298875800706295, "Median": -1.2670537740465992, "1st Quartile": -2.215815661428518, "3rd Quartile": 0.5708013588594589, "Standard Deviation": 3.2583087340586507}, "Cluster Statistics": {"Mean": 0.20343135106579335, "Median": 0.20343135106579335, "1st Quartile": -0.531811211490403, "3rd Quartile": 0.9386739136219897, "Standard Deviation": 1.4704851251123925}}}, {"1": {"Comparison": "Cluster elements in lowest 25%", "Credit Rating Statistics": {"Mean": 1.0435980604874229, "Median": -0.21707314176801296, "1st Quartile": -2.4278193469137213, "3rd Quartile": 4.833345978136686, "Standard Deviation": 3.9352038873742665}, "Cluster Statistics": {"Mean": -3.307003340314803, "Median": -3.307003340314803, "1st Quartile": -3.5255448035276618, "3rd Quartile": -3.0884618771019445, "Standard Deviation": 0.437082926425717}}}, {"2": {"Comparison": "Cluster elements in lower half", "Credit Rating Statistics": {"Mean": 2.572890299473797, "Median": 2.2438619853815793, "1st Quartile": 1.1120566211504648, "3rd Quartile": 3.198358241352911, "Standard Deviation": 2.4801568352795327}, "Cluster Statistics": {"Mean": 1.7967531728696162, "Median": 1.7967531728696162, "1st Quartile": 1.3586977932015136, "3rd Quartile": 2.234808552537719, "Standard Deviation": 0.8761107593362047}}}, {"4": {"Comparison": "Cluster elements in highest 75%", "Credit Rating Statistics": {"Mean": 0.4635441635657343, "Median": -0.632177571171495, "1st Quartile": -1.8790696754437806, "3rd Quartile": 0.6937871514299992, "Standard Deviation": 3.93098565117991}, "Cluster Statistics": {"Mean": 0.6937871514299992, "Median": 0.6937871514299992, "1st Quartile": 0.5417153061582872, "3rd Quartile": 0.8458589967017112, "Standard Deviation": 0.30414369054342394}}}, {"10": {"Comparison": "Cluster elements in lower half", "Credit Rating Statistics": {"Mean": -0.1794992623327809, "Median": -0.14572521154487528, "1st Quartile": -0.3611615787722374, "3rd Quartile": -0.09763668117020935, "Standard Deviation": 0.30254185521759536}, "Cluster Statistics": {"Mean": -0.34419445972619966, "Median": -0.34419445972619966, "1st Quartile": -0.4684552332428307, "3rd Quartile": -0.21993368620956855, "Standard Deviation": 0.24852154703326215}}}]}, "CLUSTER 1": {"RATING BBB-": [{"0": {"Comparison": "Cluster elements in lower half", "Credit Rating Statistics": {"Mean": -1.4204593265994347, "Median": -1.4081144746898047, "1st Quartile": -2.6029579389148125, "3rd Quartile": -0.6612520594102711, "Standard Deviation": 1.3372982596865264}, "Cluster Statistics": {"Mean": -1.8071026053323, "Median": -1.9586438691294503, "1st Quartile": -2.649850276587671, "3rd Quartile": -1.3682872922896938, "Standard Deviation": 1.019792413351338}}}, {"1": {"Comparison": "Cluster elements in lower half", "Credit Rating Statistics": {"Mean": -0.00532724816114692, "Median": -0.17199007463595933, "1st Quartile": -0.4354131965364312, "3rd Quartile": 0.7024841110897838, "Standard Deviation": 1.1461881334006636}, "Cluster Statistics": {"Mean": -0.28639033638931144, "Median": -0.20942447062906056, "1st Quartile": -0.529690361493566, "3rd Quartile": 0.08164651667288578, "Standard Deviation": 0.9898130596512198}}}, {"2": {"Comparison": "Cluster elements in upper half", "Credit Rating Statistics": {"Mean": -0.3384527333072271, "Median": -0.6699470341697393, "1st Quartile": -0.7900441639725053, "3rd Quartile": 0.3403379486160202, "Standard Deviation": 0.8133036033331695}, "Cluster Statistics": {"Mean": -0.5371566255130226, "Median": -0.6853503255688063, "1st Quartile": -0.8346894374748213, "3rd Quartile": 0.005497217974975543, "Standard Deviation": 0.7037925018188085}}}, {"3": {"Comparison": "Cluster elements in upper half", "Credit Rating Statistics": {"Mean": -0.49996252398238966, "Median": -0.6009685174315997, "1st Quartile": -0.7066182926359421, "3rd Quartile": -0.11842768153224542, "Standard Deviation": 0.4517923221073435}, "Cluster Statistics": {"Mean": -0.5679665241103252, "Median": -0.6215210929649206, "1st Quartile": -0.7388906047047924, "3rd Quartile": -0.2589297592451862, "Standard Deviation": 0.45361203445293946}}}, {"4": {"Comparison": "Cluster elements in upper half", "Credit Rating Statistics": {"Mean": -0.2738214554933514, "Median": -0.1329060878813084, "1st Quartile": -0.3254465452688259, "3rd Quartile": 0.03646700016412463, "Standard Deviation": 0.5844445545066381}, "Cluster Statistics": {"Mean": -0.058027494430823064, "Median": -0.10334613523084138, "1st Quartile": -0.13963157423268238, "3rd Quartile": 0.09159359153637411, "Standard Deviation": 0.2693240453873635}}}], "RATING BB-": [{"0": {"Comparison": "Cluster elements in upper half", "Credit Rating Statistics": {"Mean": -2.1885080951352873, "Median": -2.507423282101638, "1st Quartile": -3.4607584196310306, "3rd Quartile": -1.0727439667819358, "Standard Deviation": 1.485087725314708}, "Cluster Statistics": {"Mean": -2.4996596606813766, "Median": -2.6221214992900563, "1st Quartile": -3.740304059744689, "3rd Quartile": -2.3927250649132192, "Standard Deviation": 1.4372511547415094}}}, {"1": {"Comparison": "Cluster elements in lower half", "Credit Rating Statistics": {"Mean": -0.7565359013107686, "Median": -0.45612502459632087, "1st Quartile": -0.9862980762999933, "3rd Quartile": -0.4133135446324082, "Standard Deviation": 0.7360173541509063}, "Cluster Statistics": {"Mean": -0.9312339476178988, "Median": -0.49888083344825285, "1st Quartile": -1.148770490583907, "3rd Quartile": -0.41336921574438884, "Standard Deviation": 0.6833369669733897}}}, {"2": {"Comparison": "Cluster elements in lower half", "Credit Rating Statistics": {"Mean": 1.3758427230358965, "Median": 0.7547433910652339, "1st Quartile": 0.17948470616933887, "3rd Quartile": 1.6020105820786172, "Standard Deviation": 1.7748266619588702}, "Cluster Statistics": {"Mean": 0.6370942498881196, "Median": 0.41062189794739395, "1st Quartile": 0.10243897557665385, "3rd Quartile": 1.098864884183074, "Standard Deviation": 0.710996326664947}}}, {"3": {"Comparison": "Cluster elements in lower half", "Credit Rating Statistics": {"Mean": -0.06814201106800595, "Median": -1.1015612525993919, "1st Quartile": -1.3420738856398153, "3rd Quartile": -0.8349121693058519, "Standard Deviation": 2.5495008414624327}, "Cluster Statistics": {"Mean": -1.201676937497917, "Median": -1.269199170556824, "1st Quartile": -1.366365457334146, "3rd Quartile": -0.93392333464196, "Standard Deviation": 0.3008934564300122}}}, {"4": {"Comparison": "Cluster elements in upper half", "Credit Rating Statistics": {"Mean": -0.39545125471833514, "Median": -0.4872076589268669, "1st Quartile": -0.720194686858596, "3rd Quartile": -0.17891496056302136, "Standard Deviation": 0.47354940898832404}, "Cluster Statistics": {"Mean": -0.27685608413586477, "Median": -0.36745941328777204, "1st Quartile": -0.6069559045659617, "3rd Quartile": -0.11606680965477112, "Standard Deviation": 0.4297789715550513}}}]}, "CLUSTER 2": {"RATING BBB+": [{"0": {"Comparison": "Cluster elements in lowest 25%", "Credit Rating Statistics": {"Mean": 4.712312896641615, "Median": 4.300921572268282, "1st Quartile": 3.0345941631793965, "3rd Quartile": 5.978640305730502, "Standard Deviation": 2.0839733131601332}, "Cluster Statistics": {"Mean": 2.4390904361254973, "Median": 2.4390904361254973, "1st Quartile": 2.4390904361254973, "3rd Quartile": 2.4390904361254973, "Standard Deviation": 0.0}}}, {"1": {"Comparison": "Cluster elements in lower half", "Credit Rating Statistics": {"Mean": 2.4958440227336975, "Median": 2.3212928946948725, "1st Quartile": 0.8691574345770341, "3rd Quartile": 3.9479794828515358, "Standard Deviation": 1.8664106680636527}, "Cluster Statistics": {"Mean": 1.0320662647260161, "Median": 1.0320662647260161, "1st Quartile": 1.0320662647260161, "3rd Quartile": 1.0320662647260161, "Standard Deviation": 0.0}}}, {"2": {"Comparison": "Cluster elements in lowest 25%", "Credit Rating Statistics": {"Mean": -0.5603971606329484, "Median": -0.7706398406653892, "1st Quartile": -1.1261784269818478, "3rd Quartile": -0.2048585743164898, "Standard Deviation": 1.0783081124981475}, "Cluster Statistics": {"Mean": -1.8412484416909798, "Median": -1.8412484416909798, "1st Quartile": -1.8412484416909798, "3rd Quartile": -1.8412484416909798, "Standard Deviation": 0.0}}}, {"3": {"Comparison": "Cluster elements in highest 75%", "Credit Rating Statistics": {"Mean": -1.2374681848537425, "Median": -0.8201251385206187, "1st Quartile": -2.010554855455124, "3rd Quartile": -0.04703846791923727, "Standard Deviation": 1.9664122570142113}, "Cluster Statistics": {"Mean": 1.0310864832793076, "Median": 1.0310864832793076, "1st Quartile": 1.0310864832793076, "3rd Quartile": 1.0310864832793076, "Standard Deviation": 0.0}}}, {"4": {"Comparison": "Cluster elements in highest 75%", "Credit Rating Statistics": {"Mean": -1.2665407642464537, "Median": -1.5276786775613684, "1st Quartile": -1.6725511133488988, "3rd Quartile": -1.1216683284589233, "Standard Deviation": 0.6551385547503185}, "Cluster Statistics": {"Mean": -0.15998860061754916, "Median": -0.15998860061754916, "1st Quartile": -0.15998860061754916, "3rd Quartile": -0.15998860061754916, "Standard Deviation": 0.0}}}], "RATING B": [{"0": {"Comparison": "Cluster elements in highest 75%", "Credit Rating Statistics": {"Mean": -1.6841419307058771, "Median": -3.0688412206343902, "1st Quartile": -3.3679464811592688, "3rd Quartile": -0.6926870252167427, "Standard Deviation": 2.393749812777197}, "Cluster Statistics": {"Mean": 1.6834671702009052, "Median": 1.6834671702009052, "1st Quartile": 1.6834671702009052, "3rd Quartile": 1.6834671702009052, "Standard Deviation": 0.0}}}, {"2": {"Comparison": "Cluster elements in highest 75%", "Credit Rating Statistics": {"Mean": 0.5266111483810383, "Median": 0.19067823979697623, "1st Quartile": -0.21948676858959232, "3rd Quartile": 1.104742611059638, "Standard Deviation": 1.107014495306632}, "Cluster Statistics": {"Mean": 2.0188069823222996, "Median": 2.0188069823222996, "1st Quartile": 2.0188069823222996, "3rd Quartile": 2.0188069823222996, "Standard Deviation": 0.0}}}, {"3": {"Comparison": "Cluster elements in lowest 25%", "Credit Rating Statistics": {"Mean": -1.384518106809389, "Median": -1.6103802950197914, "1st Quartile": -1.685141879930658, "3rd Quartile": -1.1968254277933217, "Standard Deviation": 0.4295061144115713}, "Cluster Statistics": {"Mean": -1.7599034648415242, "Median": -1.7599034648415242, "1st Quartile": -1.7599034648415242, "3rd Quartile": -1.7599034648415242, "Standard Deviation": 0.0}}}, {"4": {"Comparison": "Cluster elements in lowest 25%", "Credit Rating Statistics": {"Mean": -0.7058329836225714, "Median": -0.38164625223986187, "1st Quartile": -0.925906981370749, "3rd Quartile": -0.3236656201830392, "Standard Deviation": 0.5425356730075785}, "Cluster Statistics": {"Mean": -1.470167710501636, "Median": -1.470167710501636, "1st Quartile": -1.470167710501636, "3rd Quartile": -1.470167710501636, "Standard Deviation": 0.0}}}, {"5": {"Comparison": "Cluster elements in highest 75%", "Credit Rating Statistics": {"Mean": 0.2026430838640095, "Median": 0.14969798889178948, "1st Quartile": 0.05452814076140451, "3rd Quartile": 0.32428547948050446, "Standard Deviation": 0.22341502352352263}, "Cluster Statistics": {"Mean": 0.49887297006921943, "Median": 0.49887297006921943, "1st Quartile": 0.49887297006921943, "3rd Quartile": 0.49887297006921943, "Standard Deviation": 0.0}}}]}}}}