{"Algorithm Parameters": {"Eps": 90.1, "MinPts": 1, "K": 32}, "Algorithm Performance": {"Silhouette Score": 0.727}, "Clusters Content Analysis": {"Predictive Power": {"Global": {"Metrics": {"Class: Upgrade": "No element of this class", "Class: Downgrade": "No element of this class"}, "Confusion Matrix": {"predicted_down_AND_was_down": 0, "predicted_up_AND_was_up": 0, "predicted_no_change_AND_was_no_change": 55, "predicted_down_BUT_was_up": 0, "predicted_down_BUT_was_no_change": 41, "predicted_no_change_BUT_was_up": 0, "predicted_no_change_BUT_was_down": 0, "predicted_up_BUT_was_down": 0, "predicted_up_BUT_was_no_change": 12}}, "Restricted to jumps to or from below B-": {"Metrics": {"Class: Upgrade": "No element of this class", "Class: Downgrade": "No element of this class"}, "Confusion Matrix": {"predicted_down_AND_was_down": 0, "predicted_up_AND_was_up": 0, "predicted_no_change_AND_was_no_change": 55, "predicted_down_BUT_was_up": 0, "predicted_down_BUT_was_no_change": 41, "predicted_no_change_BUT_was_up": 0, "predicted_no_change_BUT_was_down": 0, "predicted_up_BUT_was_down": 0, "predicted_up_BUT_was_no_change": 12}}}, "Share of total companies in each clusters": [0.009259259259259259, 0.009259259259259259, 0.009259259259259259, 0.009259259259259259, 0.009259259259259259, 0.009259259259259259, 0.009259259259259259, 0.009259259259259259, 0.009259259259259259, 0.027777777777777776, 0.009259259259259259, 0.009259259259259259, 0.009259259259259259, 0.009259259259259259, 0.018518518518518517, 0.009259259259259259, 0.009259259259259259, 0.009259259259259259, 0.027777777777777776, 0.009259259259259259, 0.2962962962962963, 0.009259259259259259, 0.018518518518518517, 0.027777777777777776, 0.009259259259259259, 0.018518518518518517, 0.018518518518518517, 0.3333333333333333, 0.009259259259259259, 0.009259259259259259, 0.009259259259259259, 0.009259259259259259, {"SUM": 1.0}], "Clusters with significant ranges (count)": 2, "Significant Clusters (count)": 1, "Cluster Credit Ratings Shares": [{"AA-": 1.0}, {"AA-": 1.0}, {"AA-": 1.0}, {"A+": 1.0}, {"A+": 1.0}, {"A": 1.0}, {"A": 1.0}, {"A-": 1.0}, {"A-": 1.0}, {"A-": 0.3333333333333333, "BBB-": 0.3333333333333333, "BB+": 0.3333333333333333}, {"A-": 1.0}, {"BBB+": 1.0}, {"BBB+": 1.0}, {"BBB+": 1.0}, {"BBB+": 0.5, "BBB": 0.5}, {"BBB+": 1.0}, {"BBB+": 1.0}, {"BBB": 1.0}, {"BBB": 0.6666666666666666, "BB+": 0.3333333333333333}, {"BBB": 1.0}, {"BBB": 1.0}, {"BBB": 1.0}, {"BBB": 0.5, "BBB-": 0.5}, {"BBB": 0.3333333333333333, "BB+": 0.3333333333333333, "B": 0.3333333333333333}, {"BBB": 1.0}, {"BBB": 0.5, "BBB-": 0.5}, {"BBB": 0.5, "BBB-": 0.5}, {"BBB": 0.8888888888888888, "BBB-": 0.027777777777777776, "BB": 0.05555555555555555, "B": 0.027777777777777776}, {"BBB-": 1.0}, {"BBB-": 1.0}, {"BB-": 1.0}, {"CCC+": 1.0}], "Share of total companies with given credit rating in each cluter": [{"AA-": 0.3333333333333333}, {"AA-": 0.3333333333333333}, {"AA-": 0.3333333333333333}, {"A+": 0.5}, {"A+": 0.5}, {"A": 0.5}, {"A": 0.5}, {"A-": 0.25}, {"A-": 0.25}, {"A-": 0.25, "BBB-": 0.14285714285714285, "BB+": 0.3333333333333333}, {"A-": 0.25}, {"BBB+": 0.16666666666666666}, {"BBB+": 0.16666666666666666}, {"BBB+": 0.16666666666666666}, {"BBB+": 0.16666666666666666, "BBB": 0.013333333333333334}, {"BBB+": 0.16666666666666666}, {"BBB+": 0.16666666666666666}, {"BBB": 0.013333333333333334}, {"BBB": 0.02666666666666667, "BB+": 0.3333333333333333}, {"BBB": 0.013333333333333334}, {"BBB": 0.4266666666666667}, {"BBB": 0.013333333333333334}, {"BBB": 0.013333333333333334, "BBB-": 0.14285714285714285}, {"BBB": 0.013333333333333334, "BB+": 0.3333333333333333, "B": 0.5}, {"BBB": 0.013333333333333334}, {"BBB": 0.013333333333333334, "BBB-": 0.14285714285714285}, {"BBB": 0.013333333333333334, "BBB-": 0.14285714285714285}, {"BBB": 0.4266666666666667, "BBB-": 0.14285714285714285, "BB": 1.0, "B": 0.5}, {"BBB-": 0.14285714285714285}, {"BBB-": 0.14285714285714285}, {"BB-": 1.0}, {"CCC+": 1.0}], "Cluster ranges": [0.0, 0.0, 0.0, 0.0, 0.0, 0.0, 0.0, 0.0, 0.0, 4.0, 0.0, 0.0, 0.0, 0.0, 1.0, 0.0, 0.0, 0.0, 2.0, 0.0, 0.0, 0.0, 1.0, 6.0, 0.0, 1.0, 1.0, 6.0, 0.0, 0.0, 0.0, 0.0], "Cluster metrics of location and dispersion": [{"Mean": 4.0, "Median": 4.0, "1st Quartile": 4.0, "3rd Quartile": 4.0, "Standard Deviation": 0.0, "Is Signficant": false}, {"Mean": 4.0, "Median": 4.0, "1st Quartile": 4.0, "3rd Quartile": 4.0, "Standard Deviation": 0.0, "Is Signficant": false}, {"Mean": 4.0, "Median": 4.0, "1st Quartile": 4.0, "3rd Quartile": 4.0, "Standard Deviation": 0.0, "Is Signficant": false}, {"Mean": 5.0, "Median": 5.0, "1st Quartile": 5.0, "3rd Quartile": 5.0, "Standard Deviation": 0.0, "Is Signficant": false}, {"Mean": 5.0, "Median": 5.0, "1st Quartile": 5.0, "3rd Quartile": 5.0, "Standard Deviation": 0.0, "Is Signficant": false}, {"Mean": 6.0, "Median": 6.0, "1st Quartile": 6.0, "3rd Quartile": 6.0, "Standard Deviation": 0.0, "Is Signficant": false}, {"Mean": 6.0, "Median": 6.0, "1st Quartile": 6.0, "3rd Quartile": 6.0, "Standard Deviation": 0.0, "Is Signficant": false}, {"Mean": 7.0, "Median": 7.0, "1st Quartile": 7.0, "3rd Quartile": 7.0, "Standard Deviation": 0.0, "Is Signficant": false}, {"Mean": 7.0, "Median": 7.0, "1st Quartile": 7.0, "3rd Quartile": 7.0, "Standard Deviation": 0.0, "Is Signficant": false}, {"Mean": 9.333333333333334, "Median": 10.0, "1st Quartile": 8.5, "3rd Quartile": 10.5, "Standard Deviation": 1.699673171197595, "Is Signficant": false}, {"Mean": 7.0, "Median": 7.0, "1st Quartile": 7.0, "3rd Quartile": 7.0, "Standard Deviation": 0.0, "Is Signficant": false}, {"Mean": 8.0, "Median": 8.0, "1st Quartile": 8.0, "3rd Quartile": 8.0, "Standard Deviation": 0.0, "Is Signficant": false}, {"Mean": 8.0, "Median": 8.0, "1st Quartile": 8.0, "3rd Quartile": 8.0, "Standard Deviation": 0.0, "Is Signficant": false}, {"Mean": 8.0, "Median": 8.0, "1st Quartile": 8.0, "3rd Quartile": 8.0, "Standard Deviation": 0.0, "Is Signficant": false}, {"Mean": 8.5, "Median": 8.5, "1st Quartile": 8.25, "3rd Quartile": 8.75, "Standard Deviation": 0.5, "Is Signficant": false}, {"Mean": 8.0, "Median": 8.0, "1st Quartile": 8.0, "3rd Quartile": 8.0, "Standard Deviation": 0.0, "Is Signficant": false}, {"Mean": 8.0, "Median": 8.0, "1st Quartile": 8.0, "3rd Quartile": 8.0, "Standard Deviation": 0.0, "Is Signficant": false}, {"Mean": 9.0, "Median": 9.0, "1st Quartile": 9.0, "3rd Quartile": 9.0, "Standard Deviation": 0.0, "Is Signficant": false}, {"Mean": 9.666666666666666, "Median": 9.0, "1st Quartile": 9.0, "3rd Quartile": 10.0, "Standard Deviation": 0.9428090415820634, "Is Signficant": false}, {"Mean": 9.0, "Median": 9.0, "1st Quartile": 9.0, "3rd Quartile": 9.0, "Standard Deviation": 0.0, "Is Signficant": false}, {"Mean": 9.0, "Median": 9.0, "1st Quartile": 9.0, "3rd Quartile": 9.0, "Standard Deviation": 0.0, "Is Signficant": false}, {"Mean": 9.0, "Median": 9.0, "1st Quartile": 9.0, "3rd Quartile": 9.0, "Standard Deviation": 0.0, "Is Signficant": false}, {"Mean": 9.5, "Median": 9.5, "1st Quartile": 9.25, "3rd Quartile": 9.75, "Standard Deviation": 0.5, "Is Signficant": false}, {"Mean": 11.666666666666666, "Median": 11.0, "1st Quartile": 10.0, "3rd Quartile": 13.0, "Standard Deviation": 2.494438257849294, "Is Signficant": true}, {"Mean": 9.0, "Median": 9.0, "1st Quartile": 9.0, "3rd Quartile": 9.0, "Standard Deviation": 0.0, "Is Signficant": false}, {"Mean": 9.5, "Median": 9.5, "1st Quartile": 9.25, "3rd Quartile": 9.75, "Standard Deviation": 0.5, "Is Signficant": false}, {"Mean": 9.5, "Median": 9.5, "1st Quartile": 9.25, "3rd Quartile": 9.75, "Standard Deviation": 0.5, "Is Signficant": false}, {"Mean": 9.36111111111111, "Median": 9.0, "1st Quartile": 9.0, "3rd Quartile": 9.0, "Standard Deviation": 1.1821068239418453, "Is Signficant": false}, {"Mean": 10.0, "Median": 10.0, "1st Quartile": 10.0, "3rd Quartile": 10.0, "Standard Deviation": 0.0, "Is Signficant": false}, {"Mean": 10.0, "Median": 10.0, "1st Quartile": 10.0, "3rd Quartile": 10.0, "Standard Deviation": 0.0, "Is Signficant": false}, {"Mean": 13.0, "Median": 13.0, "1st Quartile": 13.0, "3rd Quartile": 13.0, "Standard Deviation": 0.0, "Is Signficant": false}, {"Mean": 17.0, "Median": 17.0, "1st Quartile": 17.0, "3rd Quartile": 17.0, "Standard Deviation": 0.0, "Is Signficant": false}], "Cluster entropies": [0, 0, 0, 0, 0, 0, 0, 0, 0, 1.584962500721156, 0, 0, 0, 0, 1.0, 0, 0, 0, 0.9182958340544896, 0, 0, 0, 1.0, 1.584962500721156, 0, 1.0, 1.0, 0.6699250014423124, 0, 0, 0, 0], "Maximum entropy": 1.584962500721156, "Weighted average entropy": 0.4109440977630893, "Incoherencies explanations": {"CLUSTER 0": {"RATING BBB": [{"Leverage": {"Comparison": "Cluster elements in lowest 25%", "Credit Rating Statistics": {"Mean": 43.67733333333335, "Median": 40.05, "1st Quartile": 40.05, "3rd Quartile": 49.95, "Standard Deviation": 6.035761721237477}, "Cluster Statistics": {"Mean": 40.05, "Median": 40.05, "1st Quartile": 40.05, "3rd Quartile": 40.05, "Standard Deviation": 0.0}}}, {"Financial Statement Lines": {"Comparison": "Cluster elements in lowest 25%", "Credit Rating Statistics": {"Mean": 3955.8526666666676, "Median": 3645.4, "1st Quartile": 675.9, "3rd Quartile": 5800.5, "Standard Deviation": 4175.127592732094}, "Cluster Statistics": {"Mean": 675.9, "Median": 675.9, "1st Quartile": 675.9, "3rd Quartile": 675.9, "Standard Deviation": 0.0}}}, {"Industry Risk": {"Comparison": "Cluster elements in lowest 25%", "Credit Rating Statistics": {"Mean": 0.5333333333333333, "Median": 1.0, "1st Quartile": -1.0, "3rd Quartile": 2.0, "Standard Deviation": 1.3984117975602022}, "Cluster Statistics": {"Mean": -1.0, "Median": -1.0, "1st Quartile": -1.0, "3rd Quartile": -1.0, "Standard Deviation": 0.0}}}, {"Country Risk": {"Comparison": "Cluster elements in highest 75%", "Credit Rating Statistics": {"Mean": 0.1225851651468049, "Median": 0.11880201839690537, "1st Quartile": 0.11880201839690537, "3rd Quartile": 0.11880201839690537, "Standard Deviation": 0.04054907401407206}, "Cluster Statistics": {"Mean": 0.11880201839690537, "Median": 0.11880201839690537, "1st Quartile": 0.11880201839690537, "3rd Quartile": 0.11880201839690537, "Standard Deviation": 0.0}}}, {"Country Diversification": {"Comparison": "Cluster elements in highest 75%", "Credit Rating Statistics": {"Mean": 0.2257697009498537, "Median": 0.0, "1st Quartile": 0.0, "3rd Quartile": 0.0, "Standard Deviation": 0.6678962228477944}, "Cluster Statistics": {"Mean": 0.0, "Median": 0.0, "1st Quartile": 0.0, "3rd Quartile": 0.0, "Standard Deviation": 0.0}}}]}, "CLUSTER 1": {"RATING BBB": [{"Leverage": {"Comparison": "Cluster elements in upper half", "Credit Rating Statistics": {"Mean": 43.67733333333335, "Median": 40.05, "1st Quartile": 40.05, "3rd Quartile": 49.95, "Standard Deviation": 6.035761721237477}, "Cluster Statistics": {"Mean": 45.15, "Median": 45.15, "1st Quartile": 45.15, "3rd Quartile": 45.15, "Standard Deviation": 0.0}}}, {"Financial Statement Lines": {"Comparison": "Cluster elements in lower half", "Credit Rating Statistics": {"Mean": 3955.8526666666676, "Median": 3645.4, "1st Quartile": 675.9, "3rd Quartile": 5800.5, "Standard Deviation": 4175.127592732094}, "Cluster Statistics": {"Mean": 921.65, "Median": 921.65, "1st Quartile": 921.65, "3rd Quartile": 921.65, "Standard Deviation": 0.0}}}, {"Industry Risk": {"Comparison": "Cluster elements in lower half", "Credit Rating Statistics": {"Mean": 0.5333333333333333, "Median": 1.0, "1st Quartile": -1.0, "3rd Quartile": 2.0, "Standard Deviation": 1.3984117975602022}, "Cluster Statistics": {"Mean": 0.0, "Median": 0.0, "1st Quartile": 0.0, "3rd Quartile": 0.0, "Standard Deviation": 0.0}}}, {"Country Risk": {"Comparison": "Cluster elements in lowest 25%", "Credit Rating Statistics": {"Mean": 0.1225851651468049, "Median": 0.11880201839690537, "1st Quartile": 0.11880201839690537, "3rd Quartile": 0.11880201839690537, "Standard Deviation": 0.04054907401407206}, "Cluster Statistics": {"Mean": 0.08722016119524709, "Median": 0.08722016119524709, "1st Quartile": 0.08722016119524709, "3rd Quartile": 0.08722016119524709, "Standard Deviation": 0.0}}}, {"Country Diversification": {"Comparison": "Cluster elements in highest 75%", "Credit Rating Statistics": {"Mean": 0.2257697009498537, "Median": 0.0, "1st Quartile": 0.0, "3rd Quartile": 0.0, "Standard Deviation": 0.6678962228477944}, "Cluster Statistics": {"Mean": 1.6608206369460177, "Median": 1.6608206369460177, "1st Quartile": 1.6608206369460177, "3rd Quartile": 1.6608206369460177, "Standard Deviation": 0.0}}}], "RATING BB+": [{"Leverage": {"Comparison": "Cluster elements in highest 75%", "Credit Rating Statistics": {"Mean": 40.60166666666667, "Median": 34.7, "1st Quartile": 33.8275, "3rd Quartile": 44.425, "Standard Deviation": 9.60656922226776}, "Cluster Statistics": {"Mean": 54.15, "Median": 54.15, "1st Quartile": 54.15, "3rd Quartile": 54.15, "Standard Deviation": 0.0}}}, {"Financial Statement Lines": {"Comparison": "Cluster elements in lowest 25%", "Credit Rating Statistics": {"Mean": 1892.1999999999998, "Median": 2346.85, "1st Quartile": 1587.525, "3rd Quartile": 2424.2, "Standard Deviation": 755.0077361634559}, "Cluster Statistics": {"Mean": 828.2, "Median": 828.2, "1st Quartile": 828.2, "3rd Quartile": 828.2, "Standard Deviation": 0.0}}}, {"Industry Risk": {"Comparison": "Cluster elements in highest 75%", "Credit Rating Statistics": {"Mean": 0.3333333333333333, "Median": 0.0, "1st Quartile": 0.0, "3rd Quartile": 0.5, "Standard Deviation": 0.4714045207910317}, "Cluster Statistics": {"Mean": 1.0, "Median": 1.0, "1st Quartile": 1.0, "3rd Quartile": 1.0, "Standard Deviation": 0.0}}}, {"Country Risk": {"Comparison": "Cluster elements are located around median", "Credit Rating Statistics": {"Mean": 0.1172855943554908, "Median": 0.11880201839690537, "1st Quartile": 0.0707454556468284, "3rd Quartile": 0.16458394508486046, "Standard Deviation": 0.07662630860836546}, "Cluster Statistics": {"Mean": 0.11880201839690537, "Median": 0.11880201839690537, "1st Quartile": 0.11880201839690537, "3rd Quartile": 0.11880201839690537, "Standard Deviation": 0.0}}}, {"Country Diversification": {"Comparison": "Cluster elements in lowest 25%", "Credit Rating Statistics": {"Mean": 0.798143693448876, "Median": 0.8908512966034439, "1st Quartile": 0.44542564830172193, "3rd Quartile": 1.197215540173314, "Standard Deviation": 0.6173243697777794}, "Cluster Statistics": {"Mean": 0.0, "Median": 0.0, "1st Quartile": 0.0, "3rd Quartile": 0.0, "Standard Deviation": 0.0}}}], "RATING B": [{"Leverage": {"Comparison": "Cluster elements in highest 75%", "Credit Rating Statistics": {"Mean": 28.777500000000003, "Median": 28.777500000000003, "1st Quartile": 26.56625, "3rd Quartile": 30.988750000000003, "Standard Deviation": 4.422500000000001}, "Cluster Statistics": {"Mean": 33.2, "Median": 33.2, "1st Quartile": 33.2, "3rd Quartile": 33.2, "Standard Deviation": 0.0}}}, {"Financial Statement Lines": {"Comparison": "Cluster elements in highest 75%", "Credit Rating Statistics": {"Mean": 762.125, "Median": 762.125, "1st Quartile": 726.9875, "3rd Quartile": 797.2625, "Standard Deviation": 70.27499999999998}, "Cluster Statistics": {"Mean": 832.4, "Median": 832.4, "1st Quartile": 832.4, "3rd Quartile": 832.4, "Standard Deviation": 0.0}}}, {"Industry Risk": {"Comparison": "Cluster elements in highest 75%", "Credit Rating Statistics": {"Mean": 0.0, "Median": 0.0, "1st Quartile": 0.0, "3rd Quartile": 0.0, "Standard Deviation": 0.0}, "Cluster Statistics": {"Mean": 0.0, "Median": 0.0, "1st Quartile": 0.0, "3rd Quartile": 0.0, "Standard Deviation": 0.0}}}, {"Country Risk": {"Comparison": "Cluster elements in lowest 25%", "Credit Rating Statistics": {"Mean": 0.11658127308423531, "Median": 0.11658127308423531, "1st Quartile": 0.11547090042790029, "3rd Quartile": 0.11769164574057034, "Standard Deviation": 0.0022207453126700527}, "Cluster Statistics": {"Mean": 0.11436052777156526, "Median": 0.11436052777156526, "1st Quartile": 0.11436052777156526, "3rd Quartile": 0.11436052777156526, "Standard Deviation": 0.0}}}, {"Country Diversification": {"Comparison": "Cluster elements in highest 75%", "Credit Rating Statistics": {"Mean": 0.26491870214680147, "Median": 0.26491870214680147, "1st Quartile": 0.13245935107340073, "3rd Quartile": 0.3973780532202022, "Standard Deviation": 0.26491870214680147}, "Cluster Statistics": {"Mean": 0.5298374042936029, "Median": 0.5298374042936029, "1st Quartile": 0.5298374042936029, "3rd Quartile": 0.5298374042936029, "Standard Deviation": 0.0}}}]}}}}