{"Algorithm Parameters": {"K": 13}, "Algorithm Performance": {"WCSS": 122473807.92749488, "Silhouette Score": 0.6288340184904289, "Calinski Harabasz Index": 4556.2465050256815}, "Clusters Content Analysis": {"Predictive Power": {"Global": {"Metrics": {"Class: Upgrade": "No element of this class", "Class: Downgrade": "No element of this class"}, "Confusion Matrix": {"predicted_down_AND_was_down": 0, "predicted_up_AND_was_up": 0, "predicted_no_change_AND_was_no_change": 10, "predicted_down_BUT_was_up": 0, "predicted_down_BUT_was_no_change": 34, "predicted_no_change_BUT_was_up": 0, "predicted_no_change_BUT_was_down": 0, "predicted_up_BUT_was_down": 0, "predicted_up_BUT_was_no_change": 36}}, "Restricted to jumps to or from below B-": {"Metrics": {"Class: Upgrade": "No element of this class", "Class: Downgrade": "No element of this class"}, "Confusion Matrix": {"predicted_down_AND_was_down": 0, "predicted_up_AND_was_up": 0, "predicted_no_change_AND_was_no_change": 10, "predicted_down_BUT_was_up": 0, "predicted_down_BUT_was_no_change": 34, "predicted_no_change_BUT_was_up": 0, "predicted_no_change_BUT_was_down": 0, "predicted_up_BUT_was_down": 0, "predicted_up_BUT_was_no_change": 36}}}, "Share of total companies in each clusters": [0.0625, 0.0625, 0.0375, 0.2125, 0.0125, 0.0875, 0.2125, 0.1875, 0.0125, 0.05, 0.025, 0.025, 0.0125, {"SUM": 1.0}], "Clusters with significant ranges (count)": 6, "Significant Clusters (count)": 1, "Cluster Credit Ratings Shares": [{"AA": 0.2, "BBB+": 0.6, "BB+": 0.2}, {"AA": 0.2, "A": 0.2, "A-": 0.2, "BBB+": 0.2, "BB": 0.2}, {"AA-": 0.3333333333333333, "BBB": 0.6666666666666666}, {"A+": 0.058823529411764705, "A": 0.058823529411764705, "A-": 0.29411764705882354, "BBB+": 0.35294117647058826, "BBB": 0.17647058823529413, "BBB-": 0.058823529411764705}, {"A+": 1.0}, {"A-": 0.14285714285714285, "BBB+": 0.2857142857142857, "BBB": 0.42857142857142855, "BB+": 0.14285714285714285}, {"A-": 0.17647058823529413, "BBB+": 0.11764705882352941, "BBB": 0.29411764705882354, "BBB-": 0.058823529411764705, "BB+": 0.058823529411764705, "BB": 0.11764705882352941, "B+": 0.11764705882352941, "B": 0.058823529411764705}, {"A-": 0.06666666666666667, "BBB+": 0.2, "BBB": 0.26666666666666666, "BBB-": 0.26666666666666666, "BB": 0.13333333333333333, "BB-": 0.06666666666666667}, {"A-": 1.0}, {"A-": 0.25, "BBB+": 0.5, "BBB": 0.25}, {"BBB+": 1.0}, {"BBB+": 1.0}, {"BB": 1.0}], "Share of total companies with given credit rating in each cluter": [{"AA": 0.5, "BBB+": 0.13043478260869565, "BB+": 0.3333333333333333}, {"AA": 0.5, "A": 0.5, "A-": 0.07692307692307693, "BBB+": 0.043478260869565216, "BB": 0.16666666666666666}, {"AA-": 1.0, "BBB": 0.1111111111111111}, {"A+": 0.5, "A": 0.5, "A-": 0.38461538461538464, "BBB+": 0.2608695652173913, "BBB": 0.16666666666666666, "BBB-": 0.16666666666666666}, {"A+": 0.5}, {"A-": 0.07692307692307693, "BBB+": 0.08695652173913043, "BBB": 0.16666666666666666, "BB+": 0.3333333333333333}, {"A-": 0.23076923076923078, "BBB+": 0.08695652173913043, "BBB": 0.2777777777777778, "BBB-": 0.16666666666666666, "BB+": 0.3333333333333333, "BB": 0.3333333333333333, "B+": 1.0, "B": 1.0}, {"A-": 0.07692307692307693, "BBB+": 0.13043478260869565, "BBB": 0.2222222222222222, "BBB-": 0.6666666666666666, "BB": 0.3333333333333333, "BB-": 1.0}, {"A-": 0.07692307692307693}, {"A-": 0.07692307692307693, "BBB+": 0.08695652173913043, "BBB": 0.05555555555555555}, {"BBB+": 0.08695652173913043}, {"BBB+": 0.08695652173913043}, {"BB": 0.16666666666666666}], "Cluster ranges": [8.0, 9.0, 5.0, 5.0, 0.0, 4.0, 8.0, 6.0, 0.0, 2.0, 0.0, 0.0, 0.0], "Cluster metrics of location and dispersion": [{"Mean": 7.6, "Median": 8.0, "1st Quartile": 8.0, "3rd Quartile": 8.0, "Standard Deviation": 2.5768197453450252, "Is Signficant": false}, {"Mean": 7.2, "Median": 7.0, "1st Quartile": 6.0, "3rd Quartile": 8.0, "Standard Deviation": 2.9257477676655586, "Is Signficant": false}, {"Mean": 7.333333333333333, "Median": 9.0, "1st Quartile": 6.5, "3rd Quartile": 9.0, "Standard Deviation": 2.357022603955158, "Is Signficant": false}, {"Mean": 7.705882352941177, "Median": 8.0, "1st Quartile": 7.0, "3rd Quartile": 8.0, "Standard Deviation": 1.1764705882352942, "Is Signficant": false}, {"Mean": 5.0, "Median": 5.0, "1st Quartile": 5.0, "3rd Quartile": 5.0, "Standard Deviation": 0.0, "Is Signficant": false}, {"Mean": 8.714285714285714, "Median": 9.0, "1st Quartile": 8.0, "3rd Quartile": 9.0, "Standard Deviation": 1.1605769149479943, "Is Signficant": false}, {"Mean": 10.0, "Median": 9.0, "1st Quartile": 8.0, "3rd Quartile": 12.0, "Standard Deviation": 2.497057091387191, "Is Signficant": true}, {"Mean": 9.6, "Median": 9.0, "1st Quartile": 8.5, "3rd Quartile": 10.0, "Standard Deviation": 1.624807680927192, "Is Signficant": false}, {"Mean": 7.0, "Median": 7.0, "1st Quartile": 7.0, "3rd Quartile": 7.0, "Standard Deviation": 0.0, "Is Signficant": false}, {"Mean": 8.0, "Median": 8.0, "1st Quartile": 7.75, "3rd Quartile": 8.25, "Standard Deviation": 0.7071067811865476, "Is Signficant": false}, {"Mean": 8.0, "Median": 8.0, "1st Quartile": 8.0, "3rd Quartile": 8.0, "Standard Deviation": 0.0, "Is Signficant": false}, {"Mean": 8.0, "Median": 8.0, "1st Quartile": 8.0, "3rd Quartile": 8.0, "Standard Deviation": 0.0, "Is Signficant": false}, {"Mean": 12.0, "Median": 12.0, "1st Quartile": 12.0, "3rd Quartile": 12.0, "Standard Deviation": 0.0, "Is Signficant": false}], "Cluster entropies": [1.3709505944546687, 2.321928094887362, 0.9182958340544896, 2.212503842372268, 0, 1.8423709931771084, 2.771902372038559, 2.389898095464287, 0, 1.5, 0, 0, 0], "Maximum entropy": 2.771902372038559, "Weighted average entropy": 2.008740687225772, "Incoherencies explanations": {"CLUSTER 0": {"RATING BBB": [{"Leverage": {"Comparison": "Cluster elements in upper half", "Credit Rating Statistics": {"Mean": 16.911312499999998, "Median": 16.639062499999998, "1st Quartile": 15.30259375, "3rd Quartile": 18.291625000000003, "Standard Deviation": 3.9920160957985362}, "Cluster Statistics": {"Mean": 16.791249999999998, "Median": 17.43825, "1st Quartile": 14.711875, "3rd Quartile": 18.220375, "Standard Deviation": 2.1099615266042178}}}, {"Profitability": {"Comparison": "Cluster elements in upper half", "Credit Rating Statistics": {"Mean": 14.736977777777774, "Median": 15.161100000000001, "1st Quartile": 11.689600000000002, "3rd Quartile": 17.82445, "Standard Deviation": 5.755432178343011}, "Cluster Statistics": {"Mean": 17.433960000000003, "Median": 16.052999999999997, "1st Quartile": 13.729, "3rd Quartile": 16.854400000000002, "Standard Deviation": 6.121206797878995}}}, {"Financial Statement Lines": {"Comparison": "Cluster elements in lowest 25%", "Credit Rating Statistics": {"Mean": 18514.11388888889, "Median": 10190.025, "1st Quartile": 5165.599999999999, "3rd Quartile": 18079.3625, "Standard Deviation": 23022.992258415434}, "Cluster Statistics": {"Mean": 2904.37, "Median": 2542.55, "1st Quartile": 2340.55, "3rd Quartile": 2643.45, "Standard Deviation": 971.6154993617587}}}, {"Liquidity": {"Comparison": "Cluster elements in lower half", "Credit Rating Statistics": {"Mean": 29.03217777777778, "Median": 24.841, "1st Quartile": 16.4237, "3rd Quartile": 38.2453, "Standard Deviation": 17.59670563383813}, "Cluster Statistics": {"Mean": 21.79804, "Median": 17.232200000000002, "1st Quartile": 11.058399999999999, "3rd Quartile": 27.255999999999993, "Standard Deviation": 13.059813603202766}}}, {"Efficiency": {"Comparison": "Cluster elements in lower half", "Credit Rating Statistics": {"Mean": 0.6232037037037037, "Median": 0.5593333333333333, "1st Quartile": 0.40783333333333327, "3rd Quartile": 0.7338333333333332, "Standard Deviation": 0.2941032853529834}, "Cluster Statistics": {"Mean": 0.4985333333333334, "Median": 0.39399999999999996, "1st Quartile": 0.38566666666666666, "3rd Quartile": 0.47100000000000003, "Standard Deviation": 0.19634579473752709}}}]}, "CLUSTER 1": {"RATING BBB+": [{"Leverage": {"Comparison": "Cluster elements in lower half", "Credit Rating Statistics": {"Mean": 16.429494565217393, "Median": 16.511625, "1st Quartile": 15.453562499999999, "3rd Quartile": 17.3155625, "Standard Deviation": 2.1095477536274436}, "Cluster Statistics": {"Mean": 15.567125000000003, "Median": 17.29275, "1st Quartile": 14.599937500000001, "3rd Quartile": 17.397125000000003, "Standard Deviation": 2.589413593927526}}}, {"Profitability": {"Comparison": "Cluster elements in lower half", "Credit Rating Statistics": {"Mean": 18.040008695652176, "Median": 18.7672, "1st Quartile": 15.823899999999998, "3rd Quartile": 20.5141, "Standard Deviation": 4.613496470320912}, "Cluster Statistics": {"Mean": 17.19193333333333, "Median": 18.845399999999998, "1st Quartile": 15.302599999999998, "3rd Quartile": 19.907999999999998, "Standard Deviation": 3.9378651723434546}}}, {"Financial Statement Lines": {"Comparison": "Cluster elements in highest 75%", "Credit Rating Statistics": {"Mean": 22819.986956521738, "Median": 15911.0, "1st Quartile": 12638.475, "3rd Quartile": 30429.575, "Standard Deviation": 16855.19515094883}, "Cluster Statistics": {"Mean": 41918.950000000004, "Median": 40939.55, "1st Quartile": 40167.025, "3rd Quartile": 43181.175, "Standard Deviation": 2556.627790990834}}}, {"Liquidity": {"Comparison": "Cluster elements in upper half", "Credit Rating Statistics": {"Mean": 22.76606086956522, "Median": 16.1372, "1st Quartile": 13.7882, "3rd Quartile": 25.0428, "Standard Deviation": 13.723803610222172}, "Cluster Statistics": {"Mean": 19.264599999999998, "Median": 19.9566, "1st Quartile": 16.5278, "3rd Quartile": 22.3474, "Standard Deviation": 4.7768115000140705}}}, {"Efficiency": {"Comparison": "Cluster elements in highest 75%", "Credit Rating Statistics": {"Mean": 0.5555434782608696, "Median": 0.47533333333333333, "1st Quartile": 0.4261666666666667, "3rd Quartile": 0.5855, "Standard Deviation": 0.45097962671666836}, "Cluster Statistics": {"Mean": 0.6283333333333334, "Median": 0.6190000000000001, "1st Quartile": 0.6063333333333334, "3rd Quartile": 0.6456666666666667, "Standard Deviation": 0.0327866278071253}}}]}, "CLUSTER 2": {"RATING A-": [{"Leverage": {"Comparison": "Cluster elements in upper half", "Credit Rating Statistics": {"Mean": 18.65196153846154, "Median": 16.831374999999998, "1st Quartile": 14.987750000000002, "3rd Quartile": 21.090249999999997, "Standard Deviation": 6.095845270429747}, "Cluster Statistics": {"Mean": 17.461624999999998, "Median": 17.396874999999998, "1st Quartile": 15.48025, "3rd Quartile": 21.090249999999997, "Standard Deviation": 3.958733717996197}}}, {"Profitability": {"Comparison": "Cluster elements in highest 75%", "Credit Rating Statistics": {"Mean": 18.880892307692303, "Median": 18.2614, "1st Quartile": 16.9986, "3rd Quartile": 19.150199999999998, "Standard Deviation": 5.468369284905204}, "Cluster Statistics": {"Mean": 19.59928, "Median": 18.880599999999998, "1st Quartile": 17.793200000000002, "3rd Quartile": 19.169999999999998, "Standard Deviation": 3.084833855104679}}}, {"Liquidity": {"Comparison": "Cluster elements in upper half", "Credit Rating Statistics": {"Mean": 33.78138461538462, "Median": 19.0278, "1st Quartile": 13.95, "3rd Quartile": 29.886199999999995, "Standard Deviation": 45.86143596728412}, "Cluster Statistics": {"Mean": 19.683, "Median": 19.0278, "1st Quartile": 13.95, "3rd Quartile": 19.942200000000003, "Standard Deviation": 7.399124580651415}}}, {"Efficiency": {"Comparison": "Cluster elements in lower half", "Credit Rating Statistics": {"Mean": 0.6269871794871796, "Median": 0.575, "1st Quartile": 0.38166666666666665, "3rd Quartile": 0.6813333333333332, "Standard Deviation": 0.38606980050409984}, "Cluster Statistics": {"Mean": 0.526, "Median": 0.575, "1st Quartile": 0.44, "3rd Quartile": 0.5870000000000001, "Standard Deviation": 0.11066887547996501}}}, {"Country Risk": {"Comparison": "Cluster elements in lowest 25%", "Credit Rating Statistics": {"Mean": 0.1900161100449323, "Median": 0.1825978044490337, "1st Quartile": 0.18204839647040827, "3rd Quartile": 0.1825978044490337, "Standard Deviation": 0.03937246570262128}, "Cluster Statistics": {"Mean": 0.17069195424064532, "Median": 0.18204839647040827, "1st Quartile": 0.17705703420285057, "3rd Quartile": 0.1825978044490337, "Standard Deviation": 0.020870985322595317}}}], "RATING BBB+": [{"Leverage": {"Comparison": "Cluster elements in lower half", "Credit Rating Statistics": {"Mean": 16.429494565217393, "Median": 16.511625, "1st Quartile": 15.453562499999999, "3rd Quartile": 17.3155625, "Standard Deviation": 2.1095477536274436}, "Cluster Statistics": {"Mean": 16.405270833333333, "Median": 16.1641875, "1st Quartile": 15.407875, "3rd Quartile": 17.70115625, "Standard Deviation": 2.233546477410639}}}, {"Profitability": {"Comparison": "Cluster elements in lowest 25%", "Credit Rating Statistics": {"Mean": 18.040008695652176, "Median": 18.7672, "1st Quartile": 15.823899999999998, "3rd Quartile": 20.5141, "Standard Deviation": 4.613496470320912}, "Cluster Statistics": {"Mean": 13.975833333333332, "Median": 14.165099999999999, "1st Quartile": 10.2426, "3rd Quartile": 17.95335, "Standard Deviation": 4.711877743768636}}}, {"Financial Statement Lines": {"Comparison": "Cluster elements in lower half", "Credit Rating Statistics": {"Mean": 22819.986956521738, "Median": 15911.0, "1st Quartile": 12638.475, "3rd Quartile": 30429.575, "Standard Deviation": 16855.19515094883}, "Cluster Statistics": {"Mean": 13379.65, "Median": 13455.975, "1st Quartile": 13181.650000000001, "3rd Quartile": 13586.1125, "Standard Deviation": 693.4574692558057}}}, {"Liquidity": {"Comparison": "Cluster elements in upper half", "Credit Rating Statistics": {"Mean": 22.76606086956522, "Median": 16.1372, "1st Quartile": 13.7882, "3rd Quartile": 25.0428, "Standard Deviation": 13.723803610222172}, "Cluster Statistics": {"Mean": 24.153366666666667, "Median": 16.764499999999998, "1st Quartile": 15.059600000000001, "3rd Quartile": 34.56545, "Standard Deviation": 13.234376199084299}}}, {"Efficiency": {"Comparison": "Cluster elements in lowest 25%", "Credit Rating Statistics": {"Mean": 0.5555434782608696, "Median": 0.47533333333333333, "1st Quartile": 0.4261666666666667, "3rd Quartile": 0.5855, "Standard Deviation": 0.45097962671666836}, "Cluster Statistics": {"Mean": 0.40922222222222215, "Median": 0.49333333333333335, "1st Quartile": 0.2525, "3rd Quartile": 0.5539166666666666, "Standard Deviation": 0.18693875672377866}}}]}, "CLUSTER 3": {"RATING AA-": [{"Industry Diversification": {"Comparison": "Cluster elements in highest 75%", "Credit Rating Statistics": {"Mean": 1.2406515772740128, "Median": 1.2406515772740128, "1st Quartile": 1.2406515772740128, "3rd Quartile": 1.2406515772740128, "Standard Deviation": 0.0}, "Cluster Statistics": {"Mean": 1.2406515772740128, "Median": 1.2406515772740128, "1st Quartile": 1.2406515772740128, "3rd Quartile": 1.2406515772740128, "Standard Deviation": 0.0}}}], "RATING BBB": [{"Leverage": {"Comparison": "Cluster elements in highest 75%", "Credit Rating Statistics": {"Mean": 16.911312499999998, "Median": 16.639062499999998, "1st Quartile": 15.30259375, "3rd Quartile": 18.291625000000003, "Standard Deviation": 3.9920160957985362}, "Cluster Statistics": {"Mean": 22.209812499999998, "Median": 22.209812499999998, "1st Quartile": 18.93415625, "3rd Quartile": 25.48546875, "Standard Deviation": 6.5513125}}}, {"Profitability": {"Comparison": "Cluster elements in lower half", "Credit Rating Statistics": {"Mean": 14.736977777777774, "Median": 15.161100000000001, "1st Quartile": 11.689600000000002, "3rd Quartile": 17.82445, "Standard Deviation": 5.755432178343011}, "Cluster Statistics": {"Mean": 12.1643, "Median": 12.1643, "1st Quartile": 11.42125, "3rd Quartile": 12.90735, "Standard Deviation": 1.4860999999999995}}}, {"Financial Statement Lines": {"Comparison": "Cluster elements in highest 75%", "Credit Rating Statistics": {"Mean": 18514.11388888889, "Median": 10190.025, "1st Quartile": 5165.599999999999, "3rd Quartile": 18079.3625, "Standard Deviation": 23022.992258415434}, "Cluster Statistics": {"Mean": 79922.975, "Median": 79922.975, "1st Quartile": 79788.9625, "3rd Quartile": 80056.9875, "Standard Deviation": 268.02500000000146}}}, {"Liquidity": {"Comparison": "Cluster elements in upper half", "Credit Rating Statistics": {"Mean": 29.03217777777778, "Median": 24.841, "1st Quartile": 16.4237, "3rd Quartile": 38.2453, "Standard Deviation": 17.59670563383813}, "Cluster Statistics": {"Mean": 27.1379, "Median": 27.1379, "1st Quartile": 26.02015, "3rd Quartile": 28.255649999999996, "Standard Deviation": 2.2354999999999983}}}, {"Efficiency": {"Comparison": "Cluster elements in highest 75%", "Credit Rating Statistics": {"Mean": 0.6232037037037037, "Median": 0.5593333333333333, "1st Quartile": 0.40783333333333327, "3rd Quartile": 0.7338333333333332, "Standard Deviation": 0.2941032853529834}, "Cluster Statistics": {"Mean": 1.0266666666666666, "Median": 1.0266666666666666, "1st Quartile": 0.738, "3rd Quartile": 1.3153333333333335, "Standard Deviation": 0.5773333333333334}}}]}, "CLUSTER 4": {}, "CLUSTER 5": {"RATING BBB": [{"Leverage": {"Comparison": "Cluster elements in lowest 25%", "Credit Rating Statistics": {"Mean": 16.911312499999998, "Median": 16.639062499999998, "1st Quartile": 15.30259375, "3rd Quartile": 18.291625000000003, "Standard Deviation": 3.9920160957985362}, "Cluster Statistics": {"Mean": 15.109124999999999, "Median": 16.7623125, "1st Quartile": 13.4318125, "3rd Quartile": 18.439625000000003, "Standard Deviation": 4.276066161825902}}}, {"Profitability": {"Comparison": "Cluster elements in upper half", "Credit Rating Statistics": {"Mean": 14.736977777777774, "Median": 15.161100000000001, "1st Quartile": 11.689600000000002, "3rd Quartile": 17.82445, "Standard Deviation": 5.755432178343011}, "Cluster Statistics": {"Mean": 15.6711, "Median": 18.298099999999998, "1st Quartile": 15.229799999999997, "3rd Quartile": 18.7394, "Standard Deviation": 5.337012880816384}}}, {"Financial Statement Lines": {"Comparison": "Cluster elements in lower half", "Credit Rating Statistics": {"Mean": 18514.11388888889, "Median": 10190.025, "1st Quartile": 5165.599999999999, "3rd Quartile": 18079.3625, "Standard Deviation": 23022.992258415434}, "Cluster Statistics": {"Mean": 7695.5125, "Median": 7922.775, "1st Quartile": 7130.3, "3rd Quartile": 8487.9875, "Standard Deviation": 985.3384928382477}}}, {"Liquidity": {"Comparison": "Cluster elements in upper half", "Credit Rating Statistics": {"Mean": 29.03217777777778, "Median": 24.841, "1st Quartile": 16.4237, "3rd Quartile": 38.2453, "Standard Deviation": 17.59670563383813}, "Cluster Statistics": {"Mean": 30.628299999999996, "Median": 17.467999999999996, "1st Quartile": 15.35615, "3rd Quartile": 32.74014999999999, "Standard Deviation": 25.479328191496727}}}, {"Efficiency": {"Comparison": "Cluster elements in upper half", "Credit Rating Statistics": {"Mean": 0.6232037037037037, "Median": 0.5593333333333333, "1st Quartile": 0.40783333333333327, "3rd Quartile": 0.7338333333333332, "Standard Deviation": 0.2941032853529834}, "Cluster Statistics": {"Mean": 0.6076666666666666, "Median": 0.6259999999999999, "1st Quartile": 0.4560833333333333, "3rd Quartile": 0.7775833333333333, "Standard Deviation": 0.223754701999012}}}], "RATING BBB-": [{"Leverage": {"Comparison": "Cluster elements in lower half", "Credit Rating Statistics": {"Mean": 17.125354166666668, "Median": 17.6155, "1st Quartile": 16.49725, "3rd Quartile": 20.2125625, "Standard Deviation": 4.092887205781937}, "Cluster Statistics": {"Mean": 16.880281250000003, "Median": 18.601375, "1st Quartile": 14.38975, "3rd Quartile": 21.09190625, "Standard Deviation": 4.992722816271418}}}, {"Profitability": {"Comparison": "Cluster elements in lower half", "Credit Rating Statistics": {"Mean": 15.1439, "Median": 15.733, "1st Quartile": 9.67275, "3rd Quartile": 20.625799999999998, "Standard Deviation": 5.534676521411768}, "Cluster Statistics": {"Mean": 12.223700000000001, "Median": 10.3585, "1st Quartile": 8.8507, "3rd Quartile": 13.7315, "Standard Deviation": 4.512687267028373}}}, {"Financial Statement Lines": {"Comparison": "Cluster elements in upper half", "Credit Rating Statistics": {"Mean": 8009.275000000001, "Median": 8305.875, "1st Quartile": 7103.3125, "3rd Quartile": 9722.375, "Standard Deviation": 2832.853467758554}, "Cluster Statistics": {"Mean": 8377.1875, "Median": 8305.875, "1st Quartile": 7632.9375, "3rd Quartile": 9050.125, "Standard Deviation": 1176.6131396804772}}}, {"Liquidity": {"Comparison": "Cluster elements in upper half", "Credit Rating Statistics": {"Mean": 27.379566666666665, "Median": 18.424799999999998, "1st Quartile": 12.50265, "3rd Quartile": 40.796099999999996, "Standard Deviation": 18.439998624517905}, "Cluster Statistics": {"Mean": 26.5761, "Median": 18.424799999999998, "1st Quartile": 14.526749999999998, "3rd Quartile": 30.47415, "Standard Deviation": 18.45488083976703}}}, {"Efficiency": {"Comparison": "Cluster elements in highest 75%", "Credit Rating Statistics": {"Mean": 0.6054444444444446, "Median": 0.6218333333333333, "1st Quartile": 0.5114166666666666, "3rd Quartile": 0.6792500000000001, "Standard Deviation": 0.19311660905100325}, "Cluster Statistics": {"Mean": 0.6907500000000001, "Median": 0.6748333333333334, "1st Quartile": 0.6218333333333333, "3rd Quartile": 0.7437500000000001, "Standard Deviation": 0.15462613962572938}}}]}}}}