{"Algorithm Parameters": {"K": 15}, "Algorithm Performance": {"WCSS": 3.861990500556227, "Silhouette Score": 0.2127216828433797, "Calinski Harabasz Index": 21.905470908400254}, "Clusters Content Analysis": {"Predictive Power": {"Global": {"Metrics": {"Class: Upgrade": "No element of this class", "Class: Downgrade": "No element of this class"}, "Confusion Matrix": {"predicted_down_AND_was_down": 0, "predicted_up_AND_was_up": 0, "predicted_no_change_AND_was_no_change": 3, "predicted_down_BUT_was_up": 0, "predicted_down_BUT_was_no_change": 44, "predicted_no_change_BUT_was_up": 0, "predicted_no_change_BUT_was_down": 0, "predicted_up_BUT_was_down": 0, "predicted_up_BUT_was_no_change": 42}}, "Restricted to jumps to or from below B-": {"Metrics": {"Class: Upgrade": "No element of this class", "Class: Downgrade": "No element of this class"}, "Confusion Matrix": {"predicted_down_AND_was_down": 0, "predicted_up_AND_was_up": 0, "predicted_no_change_AND_was_no_change": 3, "predicted_down_BUT_was_up": 0, "predicted_down_BUT_was_no_change": 44, "predicted_no_change_BUT_was_up": 0, "predicted_no_change_BUT_was_down": 0, "predicted_up_BUT_was_down": 0, "predicted_up_BUT_was_no_change": 42}}}, "Share of total companies in each clusters": [0.056179775280898875, 0.056179775280898875, 0.06741573033707865, 0.033707865168539325, 0.07865168539325842, 0.033707865168539325, 0.033707865168539325, 0.12359550561797752, 0.02247191011235955, 0.056179775280898875, 0.1348314606741573, 0.011235955056179775, 0.033707865168539325, 0.07865168539325842, 0.1797752808988764, {"SUM": 0.9999999999999999}], "Clusters with significant ranges (count)": 10, "Significant Clusters (count)": 8, "Cluster Credit Ratings Shares": [{"A": 0.2, "B+": 0.2, "BBB-": 0.2, "BB+": 0.2, "CCC": 0.2}, {"A-": 0.2, "BBB+": 0.2, "BB+": 0.2, "B-": 0.2, "CCC": 0.2}, {"BBB+": 0.5, "A-": 0.16666666666666666, "BBB": 0.16666666666666666, "BBB-": 0.16666666666666666}, {"BBB-": 0.3333333333333333, "BBB+": 0.3333333333333333, "B+": 0.3333333333333333}, {"BBB-": 0.14285714285714285, "B+": 0.2857142857142857, "BB": 0.14285714285714285, "BB-": 0.2857142857142857, "B": 0.14285714285714285}, {"AA": 0.3333333333333333, "B": 0.3333333333333333, "B-": 0.3333333333333333}, {"AA-": 0.6666666666666666, "A-": 0.3333333333333333}, {"AA-": 0.09090909090909091, "A-": 0.09090909090909091, "BBB": 0.09090909090909091, "BBB-": 0.18181818181818182, "BB+": 0.18181818181818182, "BB": 0.09090909090909091, "B+": 0.2727272727272727}, {"AA-": 0.5, "A+": 0.5}, {"A": 0.2, "BB+": 0.2, "BB": 0.2, "B+": 0.2, "B": 0.2}, {"A-": 0.08333333333333333, "BBB": 0.25, "BBB-": 0.3333333333333333, "BB": 0.16666666666666666, "BB-": 0.08333333333333333, "B": 0.08333333333333333}, {"BBB+": 1.0}, {"BBB+": 0.6666666666666666, "CCC": 0.3333333333333333}, {"BBB-": 0.14285714285714285, "BB-": 0.14285714285714285, "B+": 0.42857142857142855, "B": 0.2857142857142857}, {"BB-": 0.1875, "B+": 0.25, "B": 0.4375, "B-": 0.125}], "Share of total companies with given credit rating in each cluter": [{"A": 0.5, "B+": 0.06666666666666667, "BBB-": 0.09090909090909091, "BB+": 0.2, "CCC": 0.3333333333333333}, {"A-": 0.2, "BBB+": 0.125, "BB+": 0.2, "B-": 0.25, "CCC": 0.3333333333333333}, {"BBB+": 0.375, "A-": 0.2, "BBB": 0.2, "BBB-": 0.09090909090909091}, {"BBB-": 0.09090909090909091, "BBB+": 0.125, "B+": 0.06666666666666667}, {"BBB-": 0.09090909090909091, "B+": 0.13333333333333333, "BB": 0.2, "BB-": 0.2857142857142857, "B": 0.07692307692307693}, {"AA": 1.0, "B": 0.07692307692307693, "B-": 0.25}, {"AA-": 0.5, "A-": 0.2}, {"AA-": 0.25, "A-": 0.2, "BBB": 0.2, "BBB-": 0.18181818181818182, "BB+": 0.4, "BB": 0.2, "B+": 0.2}, {"AA-": 0.25, "A+": 1.0}, {"A": 0.5, "BB+": 0.2, "BB": 0.2, "B+": 0.06666666666666667, "B": 0.07692307692307693}, {"A-": 0.2, "BBB": 0.6, "BBB-": 0.36363636363636365, "BB": 0.4, "BB-": 0.14285714285714285, "B": 0.07692307692307693}, {"BBB+": 0.125}, {"BBB+": 0.25, "CCC": 0.3333333333333333}, {"BBB-": 0.09090909090909091, "BB-": 0.14285714285714285, "B+": 0.2, "B": 0.15384615384615385}, {"BB-": 0.42857142857142855, "B+": 0.26666666666666666, "B": 0.5384615384615384, "B-": 0.5}], "Cluster ranges": [12.0, 11.0, 3.0, 6.0, 5.0, 13.0, 3.0, 10.0, 1.0, 9.0, 8.0, 0.0, 10.0, 5.0, 3.0], "Cluster metrics of location and dispersion": [{"Mean": 11.8, "Median": 11.0, "1st Quartile": 10.0, "3rd Quartile": 14.0, "Standard Deviation": 4.019950248448356, "Is Signficant": true}, {"Mean": 12.0, "Median": 11.0, "1st Quartile": 8.0, "3rd Quartile": 16.0, "Standard Deviation": 4.33589667773576, "Is Signficant": true}, {"Mean": 8.333333333333334, "Median": 8.0, "1st Quartile": 8.0, "3rd Quartile": 8.75, "Standard Deviation": 0.9428090415820634, "Is Signficant": false}, {"Mean": 10.666666666666666, "Median": 10.0, "1st Quartile": 9.0, "3rd Quartile": 12.0, "Standard Deviation": 2.494438257849294, "Is Signficant": true}, {"Mean": 13.0, "Median": 13.0, "1st Quartile": 12.5, "3rd Quartile": 14.0, "Standard Deviation": 1.5118578920369088, "Is Signficant": false}, {"Mean": 11.333333333333334, "Median": 15.0, "1st Quartile": 9.0, "3rd Quartile": 15.5, "Standard Deviation": 5.90668171555645, "Is Signficant": true}, {"Mean": 5.0, "Median": 4.0, "1st Quartile": 4.0, "3rd Quartile": 5.5, "Standard Deviation": 1.4142135623730951, "Is Signficant": false}, {"Mean": 10.545454545454545, "Median": 11.0, "1st Quartile": 9.5, "3rd Quartile": 13.0, "Standard Deviation": 2.9653648055091075, "Is Signficant": true}, {"Mean": 4.5, "Median": 4.5, "1st Quartile": 4.25, "3rd Quartile": 4.75, "Standard Deviation": 0.5, "Is Signficant": false}, {"Mean": 11.6, "Median": 12.0, "1st Quartile": 11.0, "3rd Quartile": 14.0, "Standard Deviation": 3.1368774282716245, "Is Signficant": true}, {"Mean": 10.5, "Median": 10.0, "1st Quartile": 9.0, "3rd Quartile": 12.0, "Standard Deviation": 2.0615528128088303, "Is Signficant": true}, {"Mean": 8.0, "Median": 8.0, "1st Quartile": 8.0, "3rd Quartile": 8.0, "Standard Deviation": 0.0, "Is Signficant": false}, {"Mean": 11.333333333333334, "Median": 8.0, "1st Quartile": 8.0, "3rd Quartile": 13.0, "Standard Deviation": 4.714045207910316, "Is Signficant": true}, {"Mean": 13.571428571428571, "Median": 14.0, "1st Quartile": 13.5, "3rd Quartile": 14.5, "Standard Deviation": 1.590789817951435, "Is Signficant": false}, {"Mean": 14.5, "Median": 15.0, "1st Quartile": 14.0, "3rd Quartile": 15.0, "Standard Deviation": 0.9354143466934853, "Is Signficant": false}], "Cluster entropies": [2.321928094887362, 2.321928094887362, 1.7924812503605778, 1.584962500721156, 2.2359263506290326, 1.584962500721156, 0.9182958340544896, 2.6635327548042547, 1.0, 2.321928094887362, 2.355388542207534, 0, 0.9182958340544896, 1.8423709931771084, 1.8496017527145814], "Maximum entropy": 2.6635327548042547, "Weighted average entropy": 2.0034673167813626, "Incoherencies explanations": {"CLUSTER 0": {"RATING B+": [{"Leverage": {"Comparison": "Cluster elements in lower half", "Credit Rating Statistics": {"Mean": 0.13460622943012748, "Median": 0.14073235398451572, "1st Quartile": 0.09998390520877534, "3rd Quartile": 0.1526994009829998, "Standard Deviation": 0.03168420562638999}, "Cluster Statistics": {"Mean": 0.13168692963932607, "Median": 0.13958006149656935, "1st Quartile": 0.12099384069703076, "3rd Quartile": 0.14632658451024305, "Standard Deviation": 0.021423881643199277}}}, {"Profitability": {"Comparison": "Cluster elements in lower half", "Credit Rating Statistics": {"Mean": 0.5738236693664795, "Median": 0.5765892010183498, "1st Quartile": 0.5016865874059678, "3rd Quartile": 0.6188665475177852, "Standard Deviation": 0.09093666297871944}, "Cluster Statistics": {"Mean": 0.5438577578084743, "Median": 0.5765892010183498, "1st Quartile": 0.5060401380338833, "3rd Quartile": 0.5980410991880032, "Standard Deviation": 0.07860316950451332}}}, {"Financial Statement Lines": {"Comparison": "Cluster elements in lower half", "Credit Rating Statistics": {"Mean": 0.106248428539555, "Median": 0.10594583862814749, "1st Quartile": 0.1048166173180144, "3rd Quartile": 0.10751630486280049, "Standard Deviation": 0.00213955044810845}, "Cluster Statistics": {"Mean": 0.10520968503449857, "Median": 0.10594583862814749, "1st Quartile": 0.10465552821827381, "3rd Quartile": 0.10613191864754778, "Standard Deviation": 0.0013130550343209769}}}, {"Liquidity": {"Comparison": "Cluster elements in upper half", "Credit Rating Statistics": {"Mean": 0.07986722647821416, "Median": 0.07290162747732251, "1st Quartile": 0.06390376372157328, "3rd Quartile": 0.09306913950655546, "Standard Deviation": 0.02754279446509726}, "Cluster Statistics": {"Mean": 0.09239825653027378, "Median": 0.09990534640057383, "1st Quartile": 0.08640348693894817, "3rd Quartile": 0.10214657105674943, "Standard Deviation": 0.013907120389228379}}}, {"Efficiency": {"Comparison": "Cluster elements in highest 75%", "Credit Rating Statistics": {"Mean": 0.1747859788945859, "Median": 0.11052753617593149, "1st Quartile": 0.09588332745032072, "3rd Quartile": 0.2030689189182978, "Standard Deviation": 0.13888114694279685}, "Cluster Statistics": {"Mean": 0.22694066990296294, "Median": 0.2632898633854164, "1st Quartile": 0.16508647708619328, "3rd Quartile": 0.3069694594609593, "Standard Deviation": 0.11866403158406737}}}]}, "CLUSTER 1": {"RATING BBB": [{"Leverage": {"Comparison": "Cluster elements in lower half", "Credit Rating Statistics": {"Mean": 0.1212962845457765, "Median": 0.11354308828845808, "1st Quartile": 0.09597768829707458, "3rd Quartile": 0.1304040445728269, "Standard Deviation": 0.03293608455317503}, "Cluster Statistics": {"Mean": 0.11330827371945318, "Median": 0.11354308828845808, "1st Quartile": 0.10476038829276632, "3rd Quartile": 0.12197356643064249, "Standard Deviation": 0.014055481849148642}}}, {"Profitability": {"Comparison": "Cluster elements in highest 75%", "Credit Rating Statistics": {"Mean": 0.5442403128210661, "Median": 0.5895943338544277, "1st Quartile": 0.478816078874711, "3rd Quartile": 0.5910270719740082, "Standard Deviation": 0.07362891620597206}, "Cluster Statistics": {"Mean": 0.6023191039084302, "Median": 0.5910270719740082, "1st Quartile": 0.5903107029142179, "3rd Quartile": 0.6086814889354315, "Standard Deviation": 0.01699251340920895}}}, {"Financial Statement Lines": {"Comparison": "Cluster elements in lower half", "Credit Rating Statistics": {"Mean": 0.1446344031105637, "Median": 0.14814294192913946, "1st Quartile": 0.1311224591890192, "3rd Quartile": 0.15320180816066728, "Standard Deviation": 0.0163834378424248}, "Cluster Statistics": {"Mean": 0.13381926798741883, "Median": 0.1311224591890192, "1st Quartile": 0.12665743101655852, "3rd Quartile": 0.13963270055907934, "Standard Deviation": 0.010764515873071515}}}, {"Liquidity": {"Comparison": "Cluster elements in upper half", "Credit Rating Statistics": {"Mean": 0.07385162587789, "Median": 0.0725637058910272, "1st Quartile": 0.06707505536463801, "3rd Quartile": 0.08112949737589252, "Standard Deviation": 0.007150727049203021}, "Cluster Statistics": {"Mean": 0.07358941954385258, "Median": 0.0725637058910272, "1st Quartile": 0.0698193806278326, "3rd Quartile": 0.07684660163345985, "Standard Deviation": 0.005783361273810886}}}, {"Efficiency": {"Comparison": "Cluster elements in lowest 25%", "Credit Rating Statistics": {"Mean": 0.1784075297451383, "Median": 0.12501158213584243, "1st Quartile": 0.10792125178093374, "3rd Quartile": 0.197388147897123, "Standard Deviation": 0.10627997427037059}, "Cluster Statistics": {"Mean": 0.1058372792401705, "Median": 0.10792125178093374, "1st Quartile": 0.09625012779233455, "3rd Quartile": 0.11646641695838808, "Standard Deviation": 0.016572176558084444}}}], "RATING BBB-": [{"Leverage": {"Comparison": "Cluster elements in highest 75%", "Credit Rating Statistics": {"Mean": 0.13249537067914027, "Median": 0.12614272407656152, "1st Quartile": 0.11877683954808801, "3rd Quartile": 0.13160561770370666, "Standard Deviation": 0.027471822455585937}, "Cluster Statistics": {"Mean": 0.1535143746701496, "Median": 0.14545718383349962, "1st Quartile": 0.1242172874143399, "3rd Quartile": 0.17475427108930935, "Standard Deviation": 0.03437391912562414}}}, {"Profitability": {"Comparison": "Cluster elements in highest 75%", "Credit Rating Statistics": {"Mean": 0.5660185686219595, "Median": 0.5773380702061419, "1st Quartile": 0.5187356757353987, "3rd Quartile": 0.6272839654473907, "Standard Deviation": 0.10063944128233061}, "Cluster Statistics": {"Mean": 0.633564818075286, "Median": 0.6272839654473907, "1st Quartile": 0.5905396715063405, "3rd Quartile": 0.6703091120163361, "Standard Deviation": 0.05016082715415433}}}, {"Financial Statement Lines": {"Comparison": "Cluster elements in lower half", "Credit Rating Statistics": {"Mean": 0.11904872955464561, "Median": 0.12141331109143919, "1st Quartile": 0.11548974561629027, "3rd Quartile": 0.12387014962714409, "Standard Deviation": 0.0073396476018027035}, "Cluster Statistics": {"Mean": 0.12010226253876766, "Median": 0.12263498218536238, "1st Quartile": 0.1171293754413798, "3rd Quartile": 0.12560786928275025, "Standard Deviation": 0.008971387597512762}}}, {"Liquidity": {"Comparison": "Cluster elements in upper half", "Credit Rating Statistics": {"Mean": 0.07472014373349321, "Median": 0.0743474837212166, "1st Quartile": 0.06417565269485534, "3rd Quartile": 0.0823101417400991, "Standard Deviation": 0.014189124895143295}, "Cluster Statistics": {"Mean": 0.07719962350500226, "Median": 0.07220021411800132, "1st Quartile": 0.06320977373961686, "3rd Quartile": 0.08619006388338671, "Standard Deviation": 0.01806394027359059}}}, {"Efficiency": {"Comparison": "Cluster elements in lower half", "Credit Rating Statistics": {"Mean": 0.12390750149862292, "Median": 0.09026843106024919, "1st Quartile": 0.07159258379616097, "3rd Quartile": 0.12921066467569378, "Standard Deviation": 0.0864528247816147}, "Cluster Statistics": {"Mean": 0.0748688616738274, "Median": 0.07159258379616097, "1st Quartile": 0.06199027774713709, "3rd Quartile": 0.08447116772285128, "Standard Deviation": 0.016540397326245095}}}]}, "CLUSTER 2": {"RATING B+": [{"Leverage": {"Comparison": "Cluster elements in upper half", "Credit Rating Statistics": {"Mean": 0.13460622943012748, "Median": 0.14073235398451572, "1st Quartile": 0.09998390520877534, "3rd Quartile": 0.1526994009829998, "Standard Deviation": 0.03168420562638999}, "Cluster Statistics": {"Mean": 0.147648784647312, "Median": 0.147648784647312, "1st Quartile": 0.1446953886809178, "3rd Quartile": 0.15060218061370617, "Standard Deviation": 0.005906791932788397}}}, {"Profitability": {"Comparison": "Cluster elements in highest 75%", "Credit Rating Statistics": {"Mean": 0.5738236693664795, "Median": 0.5765892010183498, "1st Quartile": 0.5016865874059678, "3rd Quartile": 0.6188665475177852, "Standard Deviation": 0.09093666297871944}, "Cluster Statistics": {"Mean": 0.7430549548895027, "Median": 0.7430549548895027, "1st Quartile": 0.7193654946588404, "3rd Quartile": 0.7667444151201651, "Standard Deviation": 0.04737892046132469}}}, {"Financial Statement Lines": {"Comparison": "Cluster elements in highest 75%", "Credit Rating Statistics": {"Mean": 0.106248428539555, "Median": 0.10594583862814749, "1st Quartile": 0.1048166173180144, "3rd Quartile": 0.10751630486280049, "Standard Deviation": 0.00213955044810845}, "Cluster Statistics": {"Mean": 0.1075932995134099, "Median": 0.1075932995134099, "1st Quartile": 0.10623973996429646, "3rd Quartile": 0.10894685906252333, "Standard Deviation": 0.002707119098226872}}}, {"Liquidity": {"Comparison": "Cluster elements in highest 75%", "Credit Rating Statistics": {"Mean": 0.07986722647821416, "Median": 0.07290162747732251, "1st Quartile": 0.06390376372157328, "3rd Quartile": 0.09306913950655546, "Standard Deviation": 0.02754279446509726}, "Cluster Statistics": {"Mean": 0.10589801252692417, "Median": 0.10589801252692417, "1st Quartile": 0.08880014620352325, "3rd Quartile": 0.12299587885032509, "Standard Deviation": 0.03419573264680183}}}, {"Efficiency": {"Comparison": "Cluster elements in lower half", "Credit Rating Statistics": {"Mean": 0.1747859788945859, "Median": 0.11052753617593149, "1st Quartile": 0.09588332745032072, "3rd Quartile": 0.2030689189182978, "Standard Deviation": 0.13888114694279685}, "Cluster Statistics": {"Mean": 0.10547299421442478, "Median": 0.10547299421442478, "1st Quartile": 0.09242590563923528, "3rd Quartile": 0.11852008278961429, "Standard Deviation": 0.026094177150378997}}}], "RATING BB-": [{"Leverage": {"Comparison": "Cluster elements in lower half", "Credit Rating Statistics": {"Mean": 0.14477242172567778, "Median": 0.15114377855277802, "1st Quartile": 0.1335412486449858, "3rd Quartile": 0.15466955304576965, "Standard Deviation": 0.01189671894790341}, "Cluster Statistics": {"Mean": 0.14292078507272768, "Median": 0.14292078507272768, "1st Quartile": 0.135341410391024, "3rd Quartile": 0.15050015975443137, "Standard Deviation": 0.015158749363407387}}}, {"Profitability": {"Comparison": "Cluster elements in highest 75%", "Credit Rating Statistics": {"Mean": 0.6212097407237741, "Median": 0.6325713084748932, "1st Quartile": 0.5862136138290643, "3rd Quartile": 0.6570917983071343, "Standard Deviation": 0.06417073239070316}, "Cluster Statistics": {"Mean": 0.6777847985165635, "Median": 0.6777847985165635, "1st Quartile": 0.6551780534957283, "3rd Quartile": 0.7003915435373987, "Standard Deviation": 0.04521349004167036}}}, {"Financial Statement Lines": {"Comparison": "Cluster elements in lower half", "Credit Rating Statistics": {"Mean": 0.10965191954869553, "Median": 0.10991661640550389, "1st Quartile": 0.10848710889943494, "3rd Quartile": 0.11068006909561012, "Standard Deviation": 0.0021788029937266544}, "Cluster Statistics": {"Mean": 0.10856854813670969, "Median": 0.10856854813670969, "1st Quartile": 0.10726358056174533, "3rd Quartile": 0.10987351571167406, "Standard Deviation": 0.002609935149928723}}}, {"Liquidity": {"Comparison": "Cluster elements in highest 75%", "Credit Rating Statistics": {"Mean": 0.07148674129263062, "Median": 0.0762072122012144, "1st Quartile": 0.059729569371712934, "3rd Quartile": 0.0783595608432548, "Standard Deviation": 0.014533025592554975}, "Cluster Statistics": {"Mean": 0.08720092058892004, "Median": 0.08720092058892004, "1st Quartile": 0.08231394996952462, "3rd Quartile": 0.09208789120831544, "Standard Deviation": 0.009773941238790808}}}, {"Efficiency": {"Comparison": "Cluster elements in highest 75%", "Credit Rating Statistics": {"Mean": 0.1334494054428297, "Median": 0.10422034915679883, "1st Quartile": 0.08390093489343475, "3rd Quartile": 0.1541052617649528, "Standard Deviation": 0.07365288898085172}, "Cluster Statistics": {"Mean": 0.2214510936169663, "Median": 0.2214510936169663, "1st Quartile": 0.1854131640091251, "3rd Quartile": 0.25748902322480743, "Standard Deviation": 0.07207585921568234}}}]}, "CLUSTER 3": {"RATING B+": [{"Leverage": {"Comparison": "Cluster elements in highest 75%", "Credit Rating Statistics": {"Mean": 0.13460622943012748, "Median": 0.14073235398451572, "1st Quartile": 0.09998390520877534, "3rd Quartile": 0.1526994009829998, "Standard Deviation": 0.03168420562638999}, "Cluster Statistics": {"Mean": 0.16276436459190138, "Median": 0.15232569444208288, "1st Quartile": 0.1465290242132993, "3rd Quartile": 0.17378036989559426, "Standard Deviation": 0.02344298356109235}}}, {"Profitability": {"Comparison": "Cluster elements in lower half", "Credit Rating Statistics": {"Mean": 0.5738236693664795, "Median": 0.5765892010183498, "1st Quartile": 0.5016865874059678, "3rd Quartile": 0.6188665475177852, "Standard Deviation": 0.09093666297871944}, "Cluster Statistics": {"Mean": 0.5645877859354617, "Median": 0.5891359943173159, "1st Quartile": 0.5347724261210336, "3rd Quartile": 0.6066772499408168, "Standard Deviation": 0.0612223520708097}}}, {"Financial Statement Lines": {"Comparison": "Cluster elements in lower half", "Credit Rating Statistics": {"Mean": 0.106248428539555, "Median": 0.10594583862814749, "1st Quartile": 0.1048166173180144, "3rd Quartile": 0.10751630486280049, "Standard Deviation": 0.00213955044810845}, "Cluster Statistics": {"Mean": 0.10499248552356667, "Median": 0.10536646085669807, "1st Quartile": 0.10403568313483481, "3rd Quartile": 0.10613627557886424, "Standard Deviation": 0.0017353927083432836}}}, {"Liquidity": {"Comparison": "Cluster elements in upper half", "Credit Rating Statistics": {"Mean": 0.07986722647821416, "Median": 0.07290162747732251, "1st Quartile": 0.06390376372157328, "3rd Quartile": 0.09306913950655546, "Standard Deviation": 0.02754279446509726}, "Cluster Statistics": {"Mean": 0.08078059518696738, "Median": 0.06332259486399744, "1st Quartile": 0.0541323750626037, "3rd Quartile": 0.09869981514984608, "Standard Deviation": 0.038426059277418774}}}, {"Efficiency": {"Comparison": "Cluster elements in upper half", "Credit Rating Statistics": {"Mean": 0.1747859788945859, "Median": 0.11052753617593149, "1st Quartile": 0.09588332745032072, "3rd Quartile": 0.2030689189182978, "Standard Deviation": 0.13888114694279685}, "Cluster Statistics": {"Mean": 0.14129812991903454, "Median": 0.11052753617593149, "1st Quartile": 0.11002515318361909, "3rd Quartile": 0.15718580978289845, "Standard Deviation": 0.04422857003003428}}}], "RATING B": [{"Leverage": {"Comparison": "Cluster elements in highest 75%", "Credit Rating Statistics": {"Mean": 0.14137920308885574, "Median": 0.14375417794975984, "1st Quartile": 0.0997613457278707, "3rd Quartile": 0.15696135984618184, "Standard Deviation": 0.04564751186715236}, "Cluster Statistics": {"Mean": 0.19684319647446058, "Median": 0.19684319647446058, "1st Quartile": 0.17150400666263568, "3rd Quartile": 0.22218238628628545, "Standard Deviation": 0.05067837962364978}}}, {"Profitability": {"Comparison": "Cluster elements in lower half", "Credit Rating Statistics": {"Mean": 0.5692804197015268, "Median": 0.5800918828518599, "1st Quartile": 0.5117992875827675, "3rd Quartile": 0.6003911009193463, "Standard Deviation": 0.07427072530959779}, "Cluster Statistics": {"Mean": 0.54653113498052, "Median": 0.54653113498052, "1st Quartile": 0.5291652112816437, "3rd Quartile": 0.5638970586793963, "Standard Deviation": 0.034731847397752535}}}, {"Financial Statement Lines": {"Comparison": "Cluster elements in lower half", "Credit Rating Statistics": {"Mean": 0.10440939857215185, "Median": 0.1044561096008014, "1st Quartile": 0.10312685880197485, "3rd Quartile": 0.1058069320374711, "Standard Deviation": 0.001321127623038938}, "Cluster Statistics": {"Mean": 0.10379526006966139, "Median": 0.10379526006966139, "1st Quartile": 0.10346105943581813, "3rd Quartile": 0.10412946070350466, "Standard Deviation": 0.0006684012676865456}}}, {"Liquidity": {"Comparison": "Cluster elements in upper half", "Credit Rating Statistics": {"Mean": 0.06799463125661748, "Median": 0.0666383944146737, "1st Quartile": 0.05551163207621266, "3rd Quartile": 0.0811569765671795, "Standard Deviation": 0.019933793085392896}, "Cluster Statistics": {"Mean": 0.07221506857361218, "Median": 0.07221506857361218, "1st Quartile": 0.06250848934709412, "3rd Quartile": 0.08192164780013023, "Standard Deviation": 0.0194131584530361}}}, {"Efficiency": {"Comparison": "Cluster elements in highest 75%", "Credit Rating Statistics": {"Mean": 0.11465764095664065, "Median": 0.10453048127139565, "1st Quartile": 0.0886596811035172, "3rd Quartile": 0.11736463670558647, "Standard Deviation": 0.05716771457993151}, "Cluster Statistics": {"Mean": 0.11859633789358733, "Median": 0.11859633789358733, "1st Quartile": 0.1179804872995869, "3rd Quartile": 0.11921218848758774, "Standard Deviation": 0.0012317011880008527}}}]}, "CLUSTER 4": {}, "CLUSTER 5": {"RATING AA": [{"Industry Diversification": {"Comparison": "Cluster elements in highest 75%", "Credit Rating Statistics": {"Mean": 0.09741805977789467, "Median": 0.09741805977789467, "1st Quartile": 0.09741805977789467, "3rd Quartile": 0.09741805977789467, "Standard Deviation": 0.0}, "Cluster Statistics": {"Mean": 0.09741805977789467, "Median": 0.09741805977789467, "1st Quartile": 0.09741805977789467, "3rd Quartile": 0.09741805977789467, "Standard Deviation": 0.0}}}], "RATING B": [{"Leverage": {"Comparison": "Cluster elements in upper half", "Credit Rating Statistics": {"Mean": 0.14137920308885574, "Median": 0.14375417794975984, "1st Quartile": 0.0997613457278707, "3rd Quartile": 0.15696135984618184, "Standard Deviation": 0.04564751186715236}, "Cluster Statistics": {"Mean": 0.14867680652695722, "Median": 0.14867680652695722, "1st Quartile": 0.14867680652695722, "3rd Quartile": 0.14867680652695722, "Standard Deviation": 0.0}}}, {"Profitability": {"Comparison": "Cluster elements in lowest 25%", "Credit Rating Statistics": {"Mean": 0.5692804197015268, "Median": 0.5800918828518599, "1st Quartile": 0.5117992875827675, "3rd Quartile": 0.6003911009193463, "Standard Deviation": 0.07427072530959779}, "Cluster Statistics": {"Mean": 0.44801783785133653, "Median": 0.44801783785133653, "1st Quartile": 0.44801783785133653, "3rd Quartile": 0.44801783785133653, "Standard Deviation": 0.0}}}, {"Financial Statement Lines": {"Comparison": "Cluster elements in lower half", "Credit Rating Statistics": {"Mean": 0.10440939857215185, "Median": 0.1044561096008014, "1st Quartile": 0.10312685880197485, "3rd Quartile": 0.1058069320374711, "Standard Deviation": 0.001321127623038938}, "Cluster Statistics": {"Mean": 0.10377310513119764, "Median": 0.10377310513119764, "1st Quartile": 0.10377310513119764, "3rd Quartile": 0.10377310513119764, "Standard Deviation": 0.0}}}, {"Liquidity": {"Comparison": "Cluster elements in highest 75%", "Credit Rating Statistics": {"Mean": 0.06799463125661748, "Median": 0.0666383944146737, "1st Quartile": 0.05551163207621266, "3rd Quartile": 0.0811569765671795, "Standard Deviation": 0.019933793085392896}, "Cluster Statistics": {"Mean": 0.0811569765671795, "Median": 0.0811569765671795, "1st Quartile": 0.0811569765671795, "3rd Quartile": 0.0811569765671795, "Standard Deviation": 0.0}}}, {"Efficiency": {"Comparison": "Cluster elements in highest 75%", "Credit Rating Statistics": {"Mean": 0.11465764095664065, "Median": 0.10453048127139565, "1st Quartile": 0.0886596811035172, "3rd Quartile": 0.11736463670558647, "Standard Deviation": 0.05716771457993151}, "Cluster Statistics": {"Mean": 0.17218731673036866, "Median": 0.17218731673036866, "1st Quartile": 0.17218731673036866, "3rd Quartile": 0.17218731673036866, "Standard Deviation": 0.0}}}], "RATING B-": [{"Leverage": {"Comparison": "Cluster elements in highest 75%", "Credit Rating Statistics": {"Mean": 0.12196359317260339, "Median": 0.12029954128941191, "1st Quartile": 0.11571518141798265, "3rd Quartile": 0.12654795304403263, "Standard Deviation": 0.011597041077903422}, "Cluster Statistics": {"Mean": 0.13975322903101822, "Median": 0.13975322903101822, "1st Quartile": 0.13975322903101822, "3rd Quartile": 0.13975322903101822, "Standard Deviation": 0.0}}}, {"Profitability": {"Comparison": "Cluster elements in lowest 25%", "Credit Rating Statistics": {"Mean": 0.4502824079204927, "Median": 0.441661797736988, "1st Quartile": 0.414245852045414, "3rd Quartile": 0.47769835361206675, "Standard Deviation": 0.060083255764054745}, "Cluster Statistics": {"Mean": 0.3761069567982078, "Median": 0.3761069567982078, "1st Quartile": 0.3761069567982078, "3rd Quartile": 0.3761069567982078, "Standard Deviation": 0.0}}}, {"Liquidity": {"Comparison": "Cluster elements in highest 75%", "Credit Rating Statistics": {"Mean": 0.05316571591821814, "Median": 0.05054482885854937, "1st Quartile": 0.047661145788573875, "3rd Quartile": 0.05604939898819364, "Standard Deviation": 0.008568697371133865}, "Cluster Statistics": {"Mean": 0.06718360242102972, "Median": 0.06718360242102972, "1st Quartile": 0.06718360242102972, "3rd Quartile": 0.06718360242102972, "Standard Deviation": 0.0}}}, {"Efficiency": {"Comparison": "Cluster elements in highest 75%", "Credit Rating Statistics": {"Mean": 0.14003560859995332, "Median": 0.14874134553690765, "1st Quartile": 0.13035790203497083, "3rd Quartile": 0.1584190521018901, "Standard Deviation": 0.026703391540971743}, "Cluster Statistics": {"Mean": 0.16632972056609288, "Median": 0.16632972056609288, "1st Quartile": 0.16632972056609288, "3rd Quartile": 0.16632972056609288, "Standard Deviation": 0.0}}}, {"Industry Risk": {"Comparison": "Cluster elements in highest 75%", "Credit Rating Statistics": {"Mean": 0.0, "Median": 0.0, "1st Quartile": 0.0, "3rd Quartile": 0.0, "Standard Deviation": 0.0}, "Cluster Statistics": {"Mean": 0.0, "Median": 0.0, "1st Quartile": 0.0, "3rd Quartile": 0.0, "Standard Deviation": 0.0}}}]}, "CLUSTER 6": {"RATING BBB-": [{"Leverage": {"Comparison": "Cluster elements in upper half", "Credit Rating Statistics": {"Mean": 0.13249537067914027, "Median": 0.12614272407656152, "1st Quartile": 0.11877683954808801, "3rd Quartile": 0.13160561770370666, "Standard Deviation": 0.027471822455585937}, "Cluster Statistics": {"Mean": 0.12965381082500071, "Median": 0.12965381082500071, "1st Quartile": 0.12965381082500071, "3rd Quartile": 0.12965381082500071, "Standard Deviation": 0.0}}}, {"Profitability": {"Comparison": "Cluster elements in lowest 25%", "Credit Rating Statistics": {"Mean": 0.5660185686219595, "Median": 0.5773380702061419, "1st Quartile": 0.5187356757353987, "3rd Quartile": 0.6272839654473907, "Standard Deviation": 0.10063944128233061}, "Cluster Statistics": {"Mean": 0.37327966776541227, "Median": 0.37327966776541227, "1st Quartile": 0.37327966776541227, "3rd Quartile": 0.37327966776541227, "Standard Deviation": 0.0}}}, {"Financial Statement Lines": {"Comparison": "Cluster elements in lower half", "Credit Rating Statistics": {"Mean": 0.11904872955464561, "Median": 0.12141331109143919, "1st Quartile": 0.11548974561629027, "3rd Quartile": 0.12387014962714409, "Standard Deviation": 0.0073396476018027035}, "Cluster Statistics": {"Mean": 0.11967072248762697, "Median": 0.11967072248762697, "1st Quartile": 0.11967072248762697, "3rd Quartile": 0.11967072248762697, "Standard Deviation": 0.0}}}, {"Liquidity": {"Comparison": "Cluster elements in upper half", "Credit Rating Statistics": {"Mean": 0.07472014373349321, "Median": 0.0743474837212166, "1st Quartile": 0.06417565269485534, "3rd Quartile": 0.0823101417400991, "Standard Deviation": 0.014189124895143295}, "Cluster Statistics": {"Mean": 0.07522805182723932, "Median": 0.07522805182723932, "1st Quartile": 0.07522805182723932, "3rd Quartile": 0.07522805182723932, "Standard Deviation": 0.0}}}, {"Efficiency": {"Comparison": "Cluster elements in highest 75%", "Credit Rating Statistics": {"Mean": 0.12390750149862292, "Median": 0.09026843106024919, "1st Quartile": 0.07159258379616097, "3rd Quartile": 0.12921066467569378, "Standard Deviation": 0.0864528247816147}, "Cluster Statistics": {"Mean": 0.3405763278709822, "Median": 0.3405763278709822, "1st Quartile": 0.3405763278709822, "3rd Quartile": 0.3405763278709822, "Standard Deviation": 0.0}}}], "RATING BBB+": [{"Leverage": {"Comparison": "Cluster elements in upper half", "Credit Rating Statistics": {"Mean": 0.14108578628711077, "Median": 0.10882423366860386, "1st Quartile": 0.10200239934940465, "3rd Quartile": 0.14886859460252322, "Standard Deviation": 0.0721289531853811}, "Cluster Statistics": {"Mean": 0.1254366413812237, "Median": 0.1254366413812237, "1st Quartile": 0.1254366413812237, "3rd Quartile": 0.1254366413812237, "Standard Deviation": 0.0}}}, {"Profitability": {"Comparison": "Cluster elements in lowest 25%", "Credit Rating Statistics": {"Mean": 0.4256290078455394, "Median": 0.402358236775878, "1st Quartile": 0.36856749713415465, "3rd Quartile": 0.4977313284630392, "Standard Deviation": 0.06058848044650233}, "Cluster Statistics": {"Mean": 0.3601118707322214, "Median": 0.3601118707322214, "1st Quartile": 0.3601118707322214, "3rd Quartile": 0.3601118707322214, "Standard Deviation": 0.0}}}, {"Financial Statement Lines": {"Comparison": "Cluster elements in lower half", "Credit Rating Statistics": {"Mean": 0.15867753053095696, "Median": 0.14731413028768803, "1st Quartile": 0.12246293902865946, "3rd Quartile": 0.17736745789841488, "Standard Deviation": 0.04908973766369435}, "Cluster Statistics": {"Mean": 0.12636671385006182, "Median": 0.12636671385006182, "1st Quartile": 0.12636671385006182, "3rd Quartile": 0.12636671385006182, "Standard Deviation": 0.0}}}, {"Liquidity": {"Comparison": "Cluster elements in highest 75%", "Credit Rating Statistics": {"Mean": 0.12075239777163113, "Median": 0.09305769496785218, "1st Quartile": 0.07831543786120873, "3rd Quartile": 0.13393214306280765, "Standard Deviation": 0.0744297844674037}, "Cluster Statistics": {"Mean": 0.17080031867770193, "Median": 0.17080031867770193, "1st Quartile": 0.17080031867770193, "3rd Quartile": 0.17080031867770193, "Standard Deviation": 0.0}}}, {"Efficiency": {"Comparison": "Cluster elements in highest 75%", "Credit Rating Statistics": {"Mean": 0.2458562153143136, "Median": 0.19061292744608882, "1st Quartile": 0.17063609757828488, "3rd Quartile": 0.31654924865730205, "Standard Deviation": 0.11581017383953501}, "Cluster Statistics": {"Mean": 0.4876306787158119, "Median": 0.4876306787158119, "1st Quartile": 0.4876306787158119, "3rd Quartile": 0.4876306787158119, "Standard Deviation": 0.0}}}], "RATING B+": [{"Leverage": {"Comparison": "Cluster elements in lowest 25%", "Credit Rating Statistics": {"Mean": 0.13460622943012748, "Median": 0.14073235398451572, "1st Quartile": 0.09998390520877534, "3rd Quartile": 0.1526994009829998, "Standard Deviation": 0.03168420562638999}, "Cluster Statistics": {"Mean": 0.0883557394508448, "Median": 0.0883557394508448, "1st Quartile": 0.0883557394508448, "3rd Quartile": 0.0883557394508448, "Standard Deviation": 0.0}}}, {"Profitability": {"Comparison": "Cluster elements in lowest 25%", "Credit Rating Statistics": {"Mean": 0.5738236693664795, "Median": 0.5765892010183498, "1st Quartile": 0.5016865874059678, "3rd Quartile": 0.6188665475177852, "Standard Deviation": 0.09093666297871944}, "Cluster Statistics": {"Mean": 0.4764491012336813, "Median": 0.4764491012336813, "1st Quartile": 0.4764491012336813, "3rd Quartile": 0.4764491012336813, "Standard Deviation": 0.0}}}, {"Financial Statement Lines": {"Comparison": "Cluster elements in lowest 25%", "Credit Rating Statistics": {"Mean": 0.106248428539555, "Median": 0.10594583862814749, "1st Quartile": 0.1048166173180144, "3rd Quartile": 0.10751630486280049, "Standard Deviation": 0.00213955044810845}, "Cluster Statistics": {"Mean": 0.10474705422084576, "Median": 0.10474705422084576, "1st Quartile": 0.10474705422084576, "3rd Quartile": 0.10474705422084576, "Standard Deviation": 0.0}}}, {"Liquidity": {"Comparison": "Cluster elements in lowest 25%", "Credit Rating Statistics": {"Mean": 0.07986722647821416, "Median": 0.07290162747732251, "1st Quartile": 0.06390376372157328, "3rd Quartile": 0.09306913950655546, "Standard Deviation": 0.02754279446509726}, "Cluster Statistics": {"Mean": 0.05513125081640182, "Median": 0.05513125081640182, "1st Quartile": 0.05513125081640182, "3rd Quartile": 0.05513125081640182, "Standard Deviation": 0.0}}}, {"Efficiency": {"Comparison": "Cluster elements in highest 75%", "Credit Rating Statistics": {"Mean": 0.1747859788945859, "Median": 0.11052753617593149, "1st Quartile": 0.09588332745032072, "3rd Quartile": 0.2030689189182978, "Standard Deviation": 0.13888114694279685}, "Cluster Statistics": {"Mean": 0.6082386363636364, "Median": 0.6082386363636364, "1st Quartile": 0.6082386363636364, "3rd Quartile": 0.6082386363636364, "Standard Deviation": 0.0}}}]}, "CLUSTER 7": {}, "CLUSTER 8": {"RATING BBB+": [{"Leverage": {"Comparison": "Cluster elements in highest 75%", "Credit Rating Statistics": {"Mean": 0.14108578628711077, "Median": 0.10882423366860386, "1st Quartile": 0.10200239934940465, "3rd Quartile": 0.14886859460252322, "Standard Deviation": 0.0721289531853811}, "Cluster Statistics": {"Mean": 0.15234410176340982, "Median": 0.15234410176340982, "1st Quartile": 0.11893392551190385, "3rd Quartile": 0.18575427801491579, "Standard Deviation": 0.06682035250301195}}}, {"Profitability": {"Comparison": "Cluster elements in upper half", "Credit Rating Statistics": {"Mean": 0.4256290078455394, "Median": 0.402358236775878, "1st Quartile": 0.36856749713415465, "3rd Quartile": 0.4977313284630392, "Standard Deviation": 0.06058848044650233}, "Cluster Statistics": {"Mean": 0.43289912567640443, "Median": 0.43289912567640443, "1st Quartile": 0.4008654206481612, "3rd Quartile": 0.4649328307046476, "Standard Deviation": 0.06406741005648639}}}, {"Financial Statement Lines": {"Comparison": "Cluster elements in highest 75%", "Credit Rating Statistics": {"Mean": 0.15867753053095696, "Median": 0.14731413028768803, "1st Quartile": 0.12246293902865946, "3rd Quartile": 0.17736745789841488, "Standard Deviation": 0.04908973766369435}, "Cluster Statistics": {"Mean": 0.20478186447048752, "Median": 0.20478186447048752, "1st Quartile": 0.1763349508837297, "3rd Quartile": 0.23322877805724535, "Standard Deviation": 0.056893827173515654}}}, {"Liquidity": {"Comparison": "Cluster elements in lower half", "Credit Rating Statistics": {"Mean": 0.12075239777163113, "Median": 0.09305769496785218, "1st Quartile": 0.07831543786120873, "3rd Quartile": 0.13393214306280765, "Standard Deviation": 0.0744297844674037}, "Cluster Statistics": {"Mean": 0.09202438886180701, "Median": 0.09202438886180701, "1st Quartile": 0.07721520769712241, "3rd Quartile": 0.10683357002649162, "Standard Deviation": 0.02961836232936921}}}, {"Efficiency": {"Comparison": "Cluster elements in upper half", "Credit Rating Statistics": {"Mean": 0.2458562153143136, "Median": 0.19061292744608882, "1st Quartile": 0.17063609757828488, "3rd Quartile": 0.31654924865730205, "Standard Deviation": 0.11581017383953501}, "Cluster Statistics": {"Mean": 0.23046581904805458, "Median": 0.23046581904805458, "1st Quartile": 0.1749122850827352, "3rd Quartile": 0.28601935301337394, "Standard Deviation": 0.11110706793063874}}}], "RATING CCC": [{"Leverage": {"Comparison": "Cluster elements in highest 75%", "Credit Rating Statistics": {"Mean": 0.18530893495214676, "Median": 0.16466305376097962, "1st Quartile": 0.15491673695755298, "3rd Quartile": 0.20537819235115698, "Standard Deviation": 0.04371153766883162}, "Cluster Statistics": {"Mean": 0.24609333094133434, "Median": 0.24609333094133434, "1st Quartile": 0.24609333094133434, "3rd Quartile": 0.24609333094133434, "Standard Deviation": 0.0}}}, {"Profitability": {"Comparison": "Cluster elements in highest 75%", "Credit Rating Statistics": {"Mean": 0.3830411356947035, "Median": 0.430830261591516, "1st Quartile": 0.34276017049177143, "3rd Quartile": 0.44721666384604175, "Standard Deviation": 0.09173879375472067}, "Cluster Statistics": {"Mean": 0.46360306610056756, "Median": 0.46360306610056756, "1st Quartile": 0.46360306610056756, "3rd Quartile": 0.46360306610056756, "Standard Deviation": 0.0}}}, {"Liquidity": {"Comparison": "Cluster elements are located around median", "Credit Rating Statistics": {"Mean": 0.09874607272258941, "Median": 0.09458252365081718, "1st Quartile": 0.08293533347623408, "3rd Quartile": 0.11247503743305863, "Standard Deviation": 0.024298085871272898}, "Cluster Statistics": {"Mean": 0.09458252365081718, "Median": 0.09458252365081718, "1st Quartile": 0.09458252365081718, "3rd Quartile": 0.09458252365081718, "Standard Deviation": 0.0}}}, {"Efficiency": {"Comparison": "Cluster elements are located around median", "Credit Rating Statistics": {"Mean": 0.0909807038978497, "Median": 0.06570863759539212, "1st Quartile": 0.064745235165173, "3rd Quartile": 0.10458013947929762, "Standard Deviation": 0.037110893307422316}, "Cluster Statistics": {"Mean": 0.06570863759539212, "Median": 0.06570863759539212, "1st Quartile": 0.06570863759539212, "3rd Quartile": 0.06570863759539212, "Standard Deviation": 0.0}}}, {"Industry Risk": {"Comparison": "Cluster elements in highest 75%", "Credit Rating Statistics": {"Mean": 0.0, "Median": 0.0, "1st Quartile": 0.0, "3rd Quartile": 0.0, "Standard Deviation": 0.0}, "Cluster Statistics": {"Mean": 0.0, "Median": 0.0, "1st Quartile": 0.0, "3rd Quartile": 0.0, "Standard Deviation": 0.0}}}]}, "CLUSTER 9": {}}}}