{"Algorithm Parameters": {"Threshold Value": 0.6, "Braching Factor": 7, "K": 2}, "Algorithm Performance": {"Calinski Harabasz Index": 12.285160428401873}, "Clusters Content Analysis": {"Predictive Power": {"Global": {"Metrics": {"Class: Upgrade": "No element of this class", "Class: Downgrade": "No element of this class"}, "Confusion Matrix": {"predicted_down_AND_was_down": 0, "predicted_up_AND_was_up": 0, "predicted_no_change_AND_was_no_change": 0, "predicted_down_BUT_was_up": 0, "predicted_down_BUT_was_no_change": 34, "predicted_no_change_BUT_was_up": 0, "predicted_no_change_BUT_was_down": 0, "predicted_up_BUT_was_down": 0, "predicted_up_BUT_was_no_change": 28}}, "Restricted to jumps to or from below B-": {"Metrics": {"Class: Upgrade": "No element of this class", "Class: Downgrade": "No element of this class"}, "Confusion Matrix": {"predicted_down_AND_was_down": 0, "predicted_up_AND_was_up": 0, "predicted_no_change_AND_was_no_change": 0, "predicted_down_BUT_was_up": 0, "predicted_down_BUT_was_no_change": 34, "predicted_no_change_BUT_was_up": 0, "predicted_no_change_BUT_was_down": 0, "predicted_up_BUT_was_down": 0, "predicted_up_BUT_was_no_change": 28}}}, "Share of total companies in each clusters": [0.5645161290322581, 0.43548387096774194, {"SUM": 1.0}], "Clusters with significant ranges (count)": 2, "Significant Clusters (count)": 0, "Cluster Credit Ratings Shares": [{"AA": 0.02857142857142857, "AA-": 0.02857142857142857, "A+": 0.05714285714285714, "A": 0.05714285714285714, "A-": 0.11428571428571428, "BBB+": 0.14285714285714285, "BBB": 0.3142857142857143, "BBB-": 0.11428571428571428, "BB+": 0.02857142857142857, "BB": 0.05714285714285714, "BB-": 0.02857142857142857, "B+": 0.02857142857142857}, {"A-": 0.18518518518518517, "BBB+": 0.5185185185185185, "BBB": 0.18518518518518517, "BBB-": 0.037037037037037035, "BB": 0.07407407407407407}], "Share of total companies with given credit rating in each cluter": [{"AA": 1.0, "AA-": 1.0, "A+": 1.0, "A": 1.0, "A-": 0.4444444444444444, "BBB+": 0.2631578947368421, "BBB": 0.6875, "BBB-": 0.8, "BB+": 1.0, "BB": 0.5, "BB-": 1.0, "B+": 1.0}, {"A-": 0.5555555555555556, "BBB+": 0.7368421052631579, "BBB": 0.3125, "BBB-": 0.2, "BB": 0.5}], "Cluster ranges": [11.0, 5.0], "Cluster metrics of location and dispersion": [{"Mean": 8.514285714285714, "Median": 9.0, "1st Quartile": 7.0, "3rd Quartile": 9.5, "Standard Deviation": 2.3344797960931998, "Is Signficant": false}, {"Mean": 8.37037037037037, "Median": 8.0, "1st Quartile": 8.0, "3rd Quartile": 9.0, "Standard Deviation": 1.2516107591641334, "Is Signficant": false}], "Cluster entropies": [3.081757637532192, 1.8466560259530953], "Maximum entropy": 3.081757637532192, "Weighted average entropy": 2.5438908066832306, "Incoherencies explanations": {"CLUSTER 0": {"RATING BBB": [{"0": {"Comparison": "Cluster elements in highest 75%", "Credit Rating Statistics": {"Mean": 0.5181804238402798, "Median": 0.9857935410761882, "1st Quartile": -1.2963686974399897, "3rd Quartile": 1.4793930231134125, "Standard Deviation": 2.79870620792162}, "Cluster Statistics": {"Mean": 1.9393338410278893, "Median": 1.2815624782999593, "1st Quartile": 0.9857935410761882, "3rd Quartile": 1.7973630893857921, "Standard Deviation": 2.1039681075954824}}}, {"1": {"Comparison": "Cluster elements in upper half", "Credit Rating Statistics": {"Mean": 0.0847662035519991, "Median": 0.1914410383687596, "1st Quartile": -1.0705247868969554, "3rd Quartile": 1.1003989406346595, "Standard Deviation": 1.918228500929441}, "Cluster Statistics": {"Mean": 0.32995934486824513, "Median": 0.37026839353313457, "1st Quartile": 0.025373421567806143, "3rd Quartile": 1.1077233132301891, "Standard Deviation": 2.043609719013783}}}, {"3": {"Comparison": "Cluster elements in upper half", "Credit Rating Statistics": {"Mean": -0.3049324404600787, "Median": -0.4018481778506823, "1st Quartile": -1.9460089326485939, "3rd Quartile": 0.47710597548413725, "Standard Deviation": 2.003115470529819}, "Cluster Statistics": {"Mean": -0.3153395802272536, "Median": -0.6939934320460108, "1st Quartile": -2.003741194037361, "3rd Quartile": 0.61609731879325, "Standard Deviation": 2.265573414863392}}}, {"4": {"Comparison": "Cluster elements in lower half", "Credit Rating Statistics": {"Mean": -0.9636442765777036, "Median": -0.7747388382254177, "1st Quartile": -1.695903914651606, "3rd Quartile": 0.0856100582089512, "Standard Deviation": 1.4109973990502294}, "Cluster Statistics": {"Mean": -1.348341424996364, "Median": -1.4173273421823447, "1st Quartile": -2.609261621799594, "3rd Quartile": -0.4559628241931242, "Standard Deviation": 1.540044156318467}}}, {"5": {"Comparison": "Cluster elements in upper half", "Credit Rating Statistics": {"Mean": 0.192265069131029, "Median": 0.24525841003235638, "1st Quartile": -0.17749724950676002, "3rd Quartile": 0.5392346199139362, "Standard Deviation": 0.7575704848022862}, "Cluster Statistics": {"Mean": 0.386648093772287, "Median": 0.3834168983342162, "1st Quartile": 0.14745611095251498, "3rd Quartile": 0.7755193508459709, "Standard Deviation": 0.7515582978021332}}}]}, "CLUSTER 1": {"RATING BBB+": [{"0": {"Comparison": "Cluster elements in lower half", "Credit Rating Statistics": {"Mean": -1.2900870795323922, "Median": -2.486535364489539, "1st Quartile": -2.8865309045262695, "3rd Quartile": -0.5074044981545388, "Standard Deviation": 2.4160719309061607}, "Cluster Statistics": {"Mean": -2.6732509399845057, "Median": -2.7119237591636653, "1st Quartile": -3.0697628867708717, "3rd Quartile": -2.4765615672577557, "Standard Deviation": 0.4737198102333195}}}, {"1": {"Comparison": "Cluster elements in upper half", "Credit Rating Statistics": {"Mean": -0.7471419439136228, "Median": -1.3580282827873191, "1st Quartile": -1.8042380328056757, "3rd Quartile": -0.10659881863532106, "Standard Deviation": 1.710864653210003}, "Cluster Statistics": {"Mean": -1.1269299658792762, "Median": -1.760625379664384, "1st Quartile": -1.899759137296892, "3rd Quartile": -1.0428673208726094, "Standard Deviation": 1.8317251556473237}}}, {"2": {"Comparison": "Cluster elements in upper half", "Credit Rating Statistics": {"Mean": -0.12451738512555799, "Median": -0.2642211452049649, "1st Quartile": -0.5775195363658618, "3rd Quartile": 0.25619599185266845, "Standard Deviation": 0.7615798659997178}, "Cluster Statistics": {"Mean": -0.24171027534815306, "Median": -0.27871416768438295, "1st Quartile": -0.623014332031372, "3rd Quartile": 0.22697775085779065, "Standard Deviation": 0.6978131450609557}}}, {"3": {"Comparison": "Cluster elements in lower half", "Credit Rating Statistics": {"Mean": -0.08040033921122619, "Median": 0.22891616449415675, "1st Quartile": -0.7352731406582459, "3rd Quartile": 0.5361929385721858, "Standard Deviation": 1.170353281152033}, "Cluster Statistics": {"Mean": 0.1732967496685601, "Median": 0.26869914252243493, "1st Quartile": 0.12706581764303343, "3rd Quartile": 0.5786026872498374, "Standard Deviation": 0.7898415137732041}}}, {"4": {"Comparison": "Cluster elements in upper half", "Credit Rating Statistics": {"Mean": -0.10100268980822638, "Median": 0.17357765122523183, "1st Quartile": -0.361193294878373, "3rd Quartile": 0.5766593094733956, "Standard Deviation": 1.2113550105025688}, "Cluster Statistics": {"Mean": 0.4289409299437453, "Median": 0.2541997126449169, "1st Quartile": 0.02987102564163188, "3rd Quartile": 0.7768976305419539, "Standard Deviation": 0.6099060564614073}}}]}}}}